{
  "today": {
    "expiration": 1662966000,
    "displayWeekday": "Sunday",
    "displayDate": "September 11, 2022",
    "printDate": "2022-09-11",
    "centerLetter": "v",
    "outerLetters": [
      "d",
      "e",
      "i",
      "n",
      "o",
      "t"
    ],
    "validLetters": [
      "v",
      "d",
      "e",
      "i",
      "n",
      "o",
      "t"
    ],
    "pangrams": [
      "devotion"
    ],
    "answers": [
      "devotion",
      "devein",
      "deveined",
      "devoid",
      "devote",
      "devoted",
      "devotee",
      "dive",
      "dived",
      "divide",
      "divided",
      "dividend",
      "divine",
      "divined",
      "divot",
      "divvied",
      "dove",
      "endive",
      "envied",
      "even",
      "evened",
      "event",
      "evident",
      "invent",
      "invented",
      "invention",
      "inventive",
      "invite",
      "invited",
      "invitee",
      "ivied",
      "nonevent",
      "oven",
      "ovine",
      "ovoid",
      "vein",
      "veined",
      "vend",
      "vended",
      "vent",
      "vented",
      "veto",
      "vetoed",
      "vetted",
      "video",
      "videoed",
      "vied",
      "vine",
      "vivid",
      "void",
      "voided",
      "voodoo",
      "vote",
      "voted",
      "votive"
    ],
    "id": 22717,
    "freeExpiration": 0,
    "editor": "Sam Ezersky"
  },
  "yesterday": {
    "displayWeekday": "Saturday",
    "displayDate": "September 10, 2022",
    "printDate": "2022-09-10",
    "centerLetter": "h",
    "outerLetters": [
      "a",
      "d",
      "e",
      "i",
      "l",
      "p"
    ],
    "validLetters": [
      "h",
      "a",
      "d",
      "e",
      "i",
      "l",
      "p"
    ],
    "pangrams": [
      "helipad"
    ],
    "answers": [
      "helipad",
      "ahead",
      "aleph",
      "alpha",
      "aphid",
      "dahlia",
      "deadhead",
      "deadheaded",
      "hail",
      "hailed",
      "halal",
      "hale",
      "hall",
      "head",
      "headed",
      "heal",
      "healed",
      "heap",
      "heaped",
      "heed",
      "heeded",
      "heel",
      "heeled",
      "held",
      "hell",
      "help",
      "helped",
      "hide",
      "hied",
      "hill",
      "hilled",
      "hippie",
      "phalli",
      "phial"
    ],
    "id": 21081,
    "freeExpiration": 0,
    "editor": "Sam Ezersky"
  }
}