{
  "today": {
    "expiration": 1688626800,
    "displayWeekday": "Wednesday",
    "displayDate": "July 5, 2023",
    "printDate": "2023-07-05",
    "centerLetter": "n",
    "outerLetters": [
      "b",
      "e",
      "f",
      "i",
      "l",
      "o"
    ],
    "validLetters": [
      "n",
      "b",
      "e",
      "f",
      "i",
      "l",
      "o"
    ],
    "pangrams": [
      "nonbelief"
    ],
    "answers": [
      "nonbelief",
      "beeline",
      "been",
      "billion",
      "blin",
      "blini",
      "bobbin",
      "bonbon",
      "bone",
      "bonobo",
      "boon",
      "ebon",
      "elfin",
      "enfeeble",
      "ennoble",
      "feline",
      "felon",
      "fennel",
      "fine",
      "infill",
      "info",
      "innie",
      "leonine",
      "lien",
      "lifeline",
      "line",
      "linen",
      "lion",
      "loin",
      "lone",
      "loon",
      "loonie",
      "nene",
      "neon",
      "nibble",
      "nine",
      "noble",
      "noel",
      "none",
      "nonillion",
      "noob",
      "noon",
      "offline",
      "onion",
      "online"
    ],
    "id": 19290,
    "freeExpiration": 0,
    "editor": "Sam Ezersky"
  },
  "yesterday": {
    "displayWeekday": "Tuesday",
    "displayDate": "July 4, 2023",
    "printDate": "2023-07-04",
    "centerLetter": "o",
    "outerLetters": [
      "a",
      "c",
      "d",
      "i",
      "m",
      "t"
    ],
    "validLetters": [
      "o",
      "a",
      "c",
      "d",
      "i",
      "m",
      "t"
    ],
    "pangrams": [
      "diatomic",
      "idiomatic"
    ],
    "answers": [
      "diatomic",
      "idiomatic",
      "ammo",
      "atom",
      "atomic",
      "cacao",
      "camo",
      "ciao",
      "coat",
      "coati",
      "coca",
      "cocci",
      "cocoa",
      "coda",
      "coma",
      "comic",
      "comma",
      "commit",
      "coot",
      "diatom",
      "ditto",
      "dodo",
      "doodad",
      "doom",
      "dotcom",
      "idiom",
      "idiot",
      "idiotic",
      "iota",
      "moat",
      "momma",
      "mood",
      "moot",
      "motto",
      "octad",
      "omit",
      "taco",
      "tattoo",
      "toad",
      "toccata",
      "tomato",
      "tomcat",
      "tomtit",
      "toot"
    ],
    "id": 23684,
    "freeExpiration": 0,
    "editor": "Sam Ezersky"
  },
  "pastPuzzles": {
    "today": {
      "displayWeekday": "Wednesday",
      "displayDate": "July 5, 2023",
      "printDate": "2023-07-05",
      "centerLetter": "n",
      "outerLetters": [
        "b",
        "e",
        "f",
        "i",
        "l",
        "o"
      ],
      "validLetters": [
        "n",
        "b",
        "e",
        "f",
        "i",
        "l",
        "o"
      ],
      "pangrams": [
        "nonbelief"
      ],
      "answers": [
        "nonbelief",
        "beeline",
        "been",
        "billion",
        "blin",
        "blini",
        "bobbin",
        "bonbon",
        "bone",
        "bonobo",
        "boon",
        "ebon",
        "elfin",
        "enfeeble",
        "ennoble",
        "feline",
        "felon",
        "fennel",
        "fine",
        "infill",
        "info",
        "innie",
        "leonine",
        "lien",
        "lifeline",
        "line",
        "linen",
        "lion",
        "loin",
        "lone",
        "loon",
        "loonie",
        "nene",
        "neon",
        "nibble",
        "nine",
        "noble",
        "noel",
        "none",
        "nonillion",
        "noob",
        "noon",
        "offline",
        "onion",
        "online"
      ],
      "id": 19290,
      "freeExpiration": 0,
      "editor": "Sam Ezersky"
    },
    "yesterday": {
      "displayWeekday": "Tuesday",
      "displayDate": "July 4, 2023",
      "printDate": "2023-07-04",
      "centerLetter": "o",
      "outerLetters": [
        "a",
        "c",
        "d",
        "i",
        "m",
        "t"
      ],
      "validLetters": [
        "o",
        "a",
        "c",
        "d",
        "i",
        "m",
        "t"
      ],
      "pangrams": [
        "diatomic",
        "idiomatic"
      ],
      "answers": [
        "diatomic",
        "idiomatic",
        "ammo",
        "atom",
        "atomic",
        "cacao",
        "camo",
        "ciao",
        "coat",
        "coati",
        "coca",
        "cocci",
        "cocoa",
        "coda",
        "coma",
        "comic",
        "comma",
        "commit",
        "coot",
        "diatom",
        "ditto",
        "dodo",
        "doodad",
        "doom",
        "dotcom",
        "idiom",
        "idiot",
        "idiotic",
        "iota",
        "moat",
        "momma",
        "mood",
        "moot",
        "motto",
        "octad",
        "omit",
        "taco",
        "tattoo",
        "toad",
        "toccata",
        "tomato",
        "tomcat",
        "tomtit",
        "toot"
      ],
      "id": 23684,
      "freeExpiration": 0,
      "editor": "Sam Ezersky"
    },
    "thisWeek": [
      {
        "displayWeekday": "Monday",
        "displayDate": "July 3, 2023",
        "printDate": "2023-07-03",
        "centerLetter": "c",
        "outerLetters": [
          "a",
          "b",
          "e",
          "h",
          "m",
          "o"
        ],
        "validLetters": [
          "c",
          "a",
          "b",
          "e",
          "h",
          "m",
          "o"
        ],
        "pangrams": [
          "beachcomb"
        ],
        "answers": [
          "beachcomb",
          "ache",
          "achoo",
          "acme",
          "beach",
          "became",
          "become",
          "beech",
          "bocce",
          "cacao",
          "cache",
          "came",
          "cameo",
          "camo",
          "chemo",
          "coach",
          "coca",
          "cocoa",
          "coho",
          "coma",
          "comb",
          "combo",
          "come",
          "comma",
          "each",
          "echo",
          "emcee",
          "hooch",
          "mace",
          "macho",
          "mecca",
          "mocha",
          "mooch"
        ],
        "id": 13131,
        "freeExpiration": 0,
        "editor": "Sam Ezersky"
      },
      {
        "displayWeekday": "Tuesday",
        "displayDate": "July 4, 2023",
        "printDate": "2023-07-04",
        "centerLetter": "o",
        "outerLetters": [
          "a",
          "c",
          "d",
          "i",
          "m",
          "t"
        ],
        "validLetters": [
          "o",
          "a",
          "c",
          "d",
          "i",
          "m",
          "t"
        ],
        "pangrams": [
          "diatomic",
          "idiomatic"
        ],
        "answers": [
          "diatomic",
          "idiomatic",
          "ammo",
          "atom",
          "atomic",
          "cacao",
          "camo",
          "ciao",
          "coat",
          "coati",
          "coca",
          "cocci",
          "cocoa",
          "coda",
          "coma",
          "comic",
          "comma",
          "commit",
          "coot",
          "diatom",
          "ditto",
          "dodo",
          "doodad",
          "doom",
          "dotcom",
          "idiom",
          "idiot",
          "idiotic",
          "iota",
          "moat",
          "momma",
          "mood",
          "moot",
          "motto",
          "octad",
          "omit",
          "taco",
          "tattoo",
          "toad",
          "toccata",
          "tomato",
          "tomcat",
          "tomtit",
          "toot"
        ],
        "id": 23684,
        "freeExpiration": 0,
        "editor": "Sam Ezersky"
      },
      {
        "displayWeekday": "Wednesday",
        "displayDate": "July 5, 2023",
        "printDate": "2023-07-05",
        "centerLetter": "n",
        "outerLetters": [
          "b",
          "e",
          "f",
          "i",
          "l",
          "o"
        ],
        "validLetters": [
          "n",
          "b",
          "e",
          "f",
          "i",
          "l",
          "o"
        ],
        "pangrams": [
          "nonbelief"
        ],
        "answers": [
          "nonbelief",
          "beeline",
          "been",
          "billion",
          "blin",
          "blini",
          "bobbin",
          "bonbon",
          "bone",
          "bonobo",
          "boon",
          "ebon",
          "elfin",
          "enfeeble",
          "ennoble",
          "feline",
          "felon",
          "fennel",
          "fine",
          "infill",
          "info",
          "innie",
          "leonine",
          "lien",
          "lifeline",
          "line",
          "linen",
          "lion",
          "loin",
          "lone",
          "loon",
          "loonie",
          "nene",
          "neon",
          "nibble",
          "nine",
          "noble",
          "noel",
          "none",
          "nonillion",
          "noob",
          "noon",
          "offline",
          "onion",
          "online"
        ],
        "id": 19290,
        "freeExpiration": 0,
        "editor": "Sam Ezersky"
      }
    ],
    "lastWeek": [
      {
        "displayWeekday": "Monday",
        "displayDate": "June 26, 2023",
        "printDate": "2023-06-26",
        "centerLetter": "m",
        "outerLetters": [
          "h",
          "i",
          "l",
          "n",
          "o",
          "t"
        ],
        "validLetters": [
          "m",
          "h",
          "i",
          "l",
          "n",
          "o",
          "t"
        ],
        "pangrams": [
          "millionth",
          "monolith"
        ],
        "answers": [
          "millionth",
          "monolith",
          "limit",
          "limn",
          "limo",
          "loom",
          "mill",
          "million",
          "mini",
          "minim",
          "minion",
          "mint",
          "mitt",
          "moil",
          "moll",
          "molt",
          "mono",
          "month",
          "moon",
          "moonlit",
          "moot",
          "moth",
          "motion",
          "motto",
          "omit",
          "tomtit"
        ],
        "id": 17219,
        "freeExpiration": 0,
        "editor": "Sam Ezersky"
      },
      {
        "displayWeekday": "Tuesday",
        "displayDate": "June 27, 2023",
        "printDate": "2023-06-27",
        "centerLetter": "a",
        "outerLetters": [
          "d",
          "k",
          "o",
          "r",
          "w",
          "y"
        ],
        "validLetters": [
          "a",
          "d",
          "k",
          "o",
          "r",
          "w",
          "y"
        ],
        "pangrams": [
          "daywork",
          "workaday",
          "workday",
          "yardwork"
        ],
        "answers": [
          "daywork",
          "workaday",
          "workday",
          "yardwork",
          "ardor",
          "array",
          "arrow",
          "arroyo",
          "award",
          "away",
          "awkward",
          "awry",
          "daddy",
          "dark",
          "doodad",
          "doorway",
          "dooryard",
          "dorado",
          "draw",
          "dray",
          "dryad",
          "dyad",
          "kayak",
          "oaky",
          "okay",
          "okra",
          "radar",
          "road",
          "roadway",
          "roadwork",
          "roar",
          "ward",
          "wary",
          "wayward",
          "yard",
          "yarrow"
        ],
        "id": 22227,
        "freeExpiration": 0,
        "editor": "Sam Ezersky"
      },
      {
        "displayWeekday": "Wednesday",
        "displayDate": "June 28, 2023",
        "printDate": "2023-06-28",
        "centerLetter": "f",
        "outerLetters": [
          "g",
          "i",
          "l",
          "n",
          "o",
          "p"
        ],
        "validLetters": [
          "f",
          "g",
          "i",
          "l",
          "n",
          "o",
          "p"
        ],
        "pangrams": [
          "flipflopping",
          "flopping"
        ],
        "answers": [
          "flipflopping",
          "flopping",
          "fifing",
          "filing",
          "fill",
          "filling",
          "fillip",
          "fining",
          "fling",
          "flinging",
          "flip",
          "flipflop",
          "flipping",
          "flog",
          "flogging",
          "flop",
          "fogging",
          "foil",
          "foiling",
          "folio",
          "fool",
          "fooling",
          "golf",
          "golfing",
          "goof",
          "goofing",
          "infill",
          "infilling",
          "info",
          "offing",
          "piffling",
          "poof"
        ],
        "id": 21111,
        "freeExpiration": 0,
        "editor": "Sam Ezersky"
      },
      {
        "displayWeekday": "Thursday",
        "displayDate": "June 29, 2023",
        "printDate": "2023-06-29",
        "centerLetter": "p",
        "outerLetters": [
          "a",
          "b",
          "e",
          "l",
          "n",
          "o"
        ],
        "validLetters": [
          "p",
          "a",
          "b",
          "e",
          "l",
          "n",
          "o"
        ],
        "pangrams": [
          "beanpole",
          "openable"
        ],
        "answers": [
          "beanpole",
          "openable",
          "apnea",
          "appall",
          "appeal",
          "appealable",
          "appellee",
          "apple",
          "bebop",
          "beep",
          "bleep",
          "bloop",
          "elope",
          "epee",
          "lapel",
          "leap",
          "lollop",
          "loop",
          "lope",
          "nape",
          "napoleon",
          "neap",
          "nope",
          "opal",
          "open",
          "paean",
          "paella",
          "palapa",
          "pale",
          "paleo",
          "pall",
          "palp",
          "palpable",
          "pane",
          "panel",
          "papa",
          "papal",
          "peal",
          "pebble",
          "peel",
          "peelable",
          "peen",
          "peep",
          "penal",
          "penne",
          "peon",
          "people",
          "plan",
          "plane",
          "plea",
          "pleb",
          "plebe",
          "plena",
          "plop",
          "poblano",
          "pole",
          "poll",
          "pollen",
          "polo",
          "pone",
          "pool",
          "poop",
          "pope",
          "poppa"
        ],
        "id": 18994,
        "freeExpiration": 0,
        "editor": "Sam Ezersky"
      },
      {
        "displayWeekday": "Friday",
        "displayDate": "June 30, 2023",
        "printDate": "2023-06-30",
        "centerLetter": "c",
        "outerLetters": [
          "d",
          "e",
          "l",
          "m",
          "o",
          "y"
        ],
        "validLetters": [
          "c",
          "d",
          "e",
          "l",
          "m",
          "o",
          "y"
        ],
        "pangrams": [
          "mollycoddle",
          "mollycoddled"
        ],
        "answers": [
          "mollycoddle",
          "mollycoddled",
          "cede",
          "ceded",
          "cell",
          "celled",
          "cello",
          "clod",
          "cloy",
          "cloyed",
          "coddle",
          "coddled",
          "code",
          "coded",
          "coed",
          "cold",
          "coldly",
          "come",
          "comedy",
          "comely",
          "commode",
          "cooed",
          "cool",
          "cooled",
          "coolly",
          "coyly",
          "cycle",
          "cycled",
          "deco",
          "decode",
          "decoded",
          "decoy",
          "decoyed",
          "emcee",
          "emceed",
          "loco"
        ],
        "id": 21036,
        "freeExpiration": 0,
        "editor": "Sam Ezersky"
      },
      {
        "displayWeekday": "Saturday",
        "displayDate": "July 1, 2023",
        "printDate": "2023-07-01",
        "centerLetter": "i",
        "outerLetters": [
          "b",
          "c",
          "e",
          "l",
          "n",
          "v"
        ],
        "validLetters": [
          "i",
          "b",
          "c",
          "e",
          "l",
          "n",
          "v"
        ],
        "pangrams": [
          "invincible",
          "vincible"
        ],
        "answers": [
          "invincible",
          "vincible",
          "beeline",
          "belie",
          "believe",
          "bible",
          "bile",
          "bill",
          "blin",
          "blini",
          "celli",
          "civic",
          "civil",
          "clinic",
          "enliven",
          "evil",
          "evince",
          "icicle",
          "incline",
          "innie",
          "lenience",
          "libel",
          "libelee",
          "lice",
          "lien",
          "line",
          "linen",
          "live",
          "liven",
          "nibble",
          "nice",
          "niece",
          "nine",
          "veil",
          "vein",
          "vibe",
          "vice",
          "vile",
          "vine"
        ],
        "id": 10120,
        "freeExpiration": 0,
        "editor": "Sam Ezersky"
      },
      {
        "displayWeekday": "Sunday",
        "displayDate": "July 2, 2023",
        "printDate": "2023-07-02",
        "centerLetter": "r",
        "outerLetters": [
          "a",
          "c",
          "d",
          "l",
          "o",
          "t"
        ],
        "validLetters": [
          "r",
          "a",
          "c",
          "d",
          "l",
          "o",
          "t"
        ],
        "pangrams": [
          "cartload",
          "doctoral"
        ],
        "answers": [
          "cartload",
          "doctoral",
          "accord",
          "actor",
          "allocator",
          "altar",
          "aorta",
          "aortal",
          "arco",
          "ardor",
          "attar",
          "attract",
          "attractor",
          "carat",
          "card",
          "carload",
          "carol",
          "carrot",
          "cart",
          "cataract",
          "collar",
          "collard",
          "color",
          "coral",
          "cord",
          "corolla",
          "corral",
          "cortado",
          "croc",
          "dart",
          "doctor",
          "dollar",
          "dolor",
          "door",
          "dorado",
          "dotard",
          "drat",
          "droll",
          "drool",
          "lard",
          "locator",
          "lord",
          "odor",
          "oral",
          "orator",
          "orca",
          "radar",
          "ratatat",
          "road",
          "roar",
          "rococo",
          "roll",
          "rood",
          "root",
          "rotator",
          "rotor",
          "taro",
          "tarot",
          "tart",
          "tartar",
          "toro",
          "tort",
          "tract",
          "tractor",
          "trod",
          "troll",
          "trot"
        ],
        "id": 16121,
        "freeExpiration": 0,
        "editor": "Sam Ezersky"
      }
    ]
  }
}