{
  "id": 1694,
  "expiration": 1690873200,
  "ourSolution": [
    "BIGRAM",
    "MUNCHES"
  ],
  "printDate": "2023-07-31",
  "sides": [
    "CER",
    "IMN",
    "ASH",
    "BGU"
  ],
  "date": "July 31, 2023",
  "dictionary": [
    "ARGH",
    "ABS",
    "ABACA",
    "ABACUS",
    "ABACUSES",
    "IBN",
    "ABEAM",
    "ABSCISE",
    "ABSCISES",
    "ABSCISIC",
    "ACACIA",
    "ACAI",
    "ACARA",
    "ACH",
    "ACHE",
    "ACHES",
    "ACHENE",
    "ACHENES",
    "ACME",
    "ACMES",
    "ACNE",
    "ACUMEN",
    "NAUSEAM",
    "AEGIS",
    "AEGISES",
    "AGA",
    "AGAMA",
    "AGAR",
    "AGARIC",
    "AGARICS",
    "AGE",
    "AGES",
    "AGEISM",
    "AGISM",
    "AGENCIES",
    "AGMA",
    "AGRARIAN",
    "AGRARIANS",
    "AIS",
    "AIGA",
    "AIR",
    "AIRS",
    "AIRBAG",
    "AIRBAGS",
    "AIRMAN",
    "AIRMEN",
    "AMANUENSIS",
    "AMANUENSES",
    "AMARI",
    "AMEN",
    "AMENS",
    "AMEBA",
    "AMEBAE",
    "AMEBIC",
    "AMUSE",
    "AMUSES",
    "ANA",
    "ANABRANCH",
    "ANABRANCHES",
    "ANAGEN",
    "ANAGENESIS",
    "ANAGRAM",
    "ANAGRAMS",
    "ANCIEN",
    "ANEURISM",
    "ANEURISMS",
    "ANURA",
    "ANURAN",
    "ANURANS",
    "ANURIA",
    "ANURIC",
    "ANUS",
    "ANUSES",
    "ARABICA",
    "ARABIS",
    "ARABISES",
    "ARACARI",
    "ARACARIS",
    "ARACHIS",
    "ARAME",
    "ARAUCARIA",
    "ARB",
    "ARBS",
    "ARGAN",
    "ARGANS",
    "ARIA",
    "ARISE",
    "ARISEN",
    "ARISES",
    "ARM",
    "ARMS",
    "ARSE",
    "ARSES",
    "ARSIS",
    "ARUM",
    "ARUMS",
    "AUMBRIES",
    "AMBRIES",
    "AURA",
    "AURAE",
    "AURAR",
    "AURIC",
    "BAB",
    "BABS",
    "BABA",
    "BABACU",
    "BABACUS",
    "BABE",
    "BABES",
    "BABICHE",
    "BABIES",
    "BACH",
    "BACHES",
    "BACNE",
    "BAE",
    "BAES",
    "BAG",
    "BAGS",
    "BAGH",
    "BAGMAN",
    "BAGMEN",
    "BAGSIES",
    "BAI",
    "BAIS",
    "BAIRN",
    "BAIRNS",
    "BAM",
    "BAMA",
    "BAN",
    "BANS",
    "BANANA",
    "BANAUSIC",
    "BANE",
    "BANES",
    "BANG",
    "BANGS",
    "BANGARANG",
    "BANGARANGS",
    "BANH",
    "BANSURI",
    "BANSURIS",
    "BAR",
    "BARS",
    "BARA",
    "BARB",
    "BARBS",
    "BARBARIAN",
    "BARBARIANS",
    "BARBARIC",
    "BARBARISM",
    "BARBARISMS",
    "BARBARISE",
    "BARBARISES",
    "BARBICAN",
    "BARBICANS",
    "BARBIE",
    "BARBIES",
    "BARGE",
    "BARGES",
    "BARGEMAN",
    "BARGEMEN",
    "BARIUM",
    "BARM",
    "BARMAN",
    "BARMEN",
    "BARN",
    "BARNS",
    "BARI",
    "BEACH",
    "BEACHES",
    "BEAM",
    "BEAMS",
    "BEAN",
    "BEANS",
    "BEANBAG",
    "BEANBAGS",
    "BEAR",
    "BEARS",
    "BEAU",
    "BEAUS",
    "BEG",
    "BEGS",
    "BEGAN",
    "BEIGE",
    "BEIGES",
    "BEIRA",
    "BEMA",
    "BEMUSE",
    "BEMUSES",
    "BEN",
    "BENS",
    "BENCH",
    "BENCHES",
    "BENGA",
    "BENUMB",
    "BENUMBS",
    "BESIEGE",
    "BESIEGES",
    "BESMEAR",
    "BESMEARS",
    "BHUNA",
    "BIB",
    "BIBS",
    "BIBI",
    "BIBIS",
    "BICARB",
    "BICHIR",
    "BICHIRS",
    "BIRI",
    "BIRIS",
    "BIEN",
    "BIG",
    "BIGS",
    "BIGA",
    "BIGRAM",
    "BIGRAMS",
    "BIS",
    "BRA",
    "BRAE",
    "BRAES",
    "BRAG",
    "BRAGS",
    "BRAISE",
    "BRAISES",
    "BRAN",
    "BRANCH",
    "BRANCHES",
    "BRANCHIA",
    "BRANCHIAE",
    "BRANE",
    "BRANES",
    "BRIAR",
    "BRIARS",
    "BRIBE",
    "BRIBES",
    "BRIG",
    "BRIGS",
    "BRIS",
    "BRISE",
    "BRISES",
    "RABE",
    "BRUH",
    "BRUISE",
    "BRUISES",
    "BRUMBIES",
    "BRUME",
    "BRUNCH",
    "BRUNCHES",
    "BRUNG",
    "CAB",
    "CABS",
    "CABANA",
    "CABMAN",
    "CABMEN",
    "CACA",
    "CACHE",
    "CACHES",
    "CAESIUM",
    "CAESURA",
    "CAGE",
    "CAGES",
    "CAIRN",
    "CAIRNS",
    "CAM",
    "CAMS",
    "CAMA",
    "CAMBIUM",
    "CAMBIA",
    "CAMBIUMS",
    "CAMBRIC",
    "CAMBRICS",
    "CAME",
    "CAMES",
    "CAN",
    "CANS",
    "CANARIES",
    "CANCAN",
    "CANCANS",
    "CANE",
    "CANES",
    "CAR",
    "CARS",
    "CARACARA",
    "CARAGANA",
    "CARAMBA",
    "CARB",
    "CARBS",
    "CARBENE",
    "CARBENES",
    "CARBIE",
    "CARBIES",
    "CARIES",
    "CARMAN",
    "CARMEN",
    "CARN",
    "CARNAGE",
    "CARSE",
    "CARSES",
    "CAUCUS",
    "CAUCUSES",
    "CAUSE",
    "CAUSES",
    "CHEMURGIC",
    "CHI",
    "CHIS",
    "CHIB",
    "CHIBS",
    "CHIC",
    "CHICA",
    "CHICANE",
    "CHICANES",
    "CHICHI",
    "CHICHIS",
    "CARNE",
    "CHENAR",
    "CHENARS",
    "CHIRM",
    "CHIRMS",
    "CHIRU",
    "CHRISM",
    "CHUM",
    "CHUMS",
    "CHURN",
    "CHURNS",
    "CICISBEI",
    "CIG",
    "CIGS",
    "CIGAR",
    "CIGARS",
    "CIS",
    "CUE",
    "CUES",
    "CUI",
    "CUM",
    "CUMBIA",
    "CUMENE",
    "CUR",
    "CURS",
    "CURACIES",
    "CURB",
    "CURBS",
    "CURIA",
    "CURIE",
    "CURIES",
    "CURIUM",
    "CURSE",
    "CURSES",
    "CUSCUS",
    "CUSCUSES",
    "SICH",
    "MEMBRA",
    "NACH",
    "EACH",
    "EAR",
    "EARS",
    "EARACHE",
    "EARACHES",
    "EARN",
    "EARNS",
    "EBAUCHE",
    "EBAUCHES",
    "EMS",
    "EMESIS",
    "GRISE",
    "EMU",
    "EMUS",
    "ENS",
    "ENCAGE",
    "ENCAGES",
    "ENEMA",
    "ENGAGE",
    "ENGAGES",
    "ENGRAM",
    "ENGRAMS",
    "ENRAGE",
    "ENRAGES",
    "ENRICH",
    "ENRICHES",
    "ENSIGN",
    "ENSIGNS",
    "ENSIGNCIES",
    "ENSUE",
    "ENSUES",
    "UNUM",
    "ESE",
    "ESES",
    "EUCIES",
    "EUNUCH",
    "GAB",
    "GABS",
    "GAG",
    "GAGS",
    "GAGA",
    "GAGE",
    "GAGES",
    "GAM",
    "GAMS",
    "GAMBA",
    "GAME",
    "GAMES",
    "GAMESMAN",
    "GAMESMEN",
    "GANACHE",
    "GANACHES",
    "GANCH",
    "GAUNCH",
    "GANCHES",
    "GAUNCHES",
    "GANG",
    "GANGS",
    "GAR",
    "GARS",
    "GARAGE",
    "GARAGES",
    "GARAM",
    "GARB",
    "GARBS",
    "GARBA",
    "GARBAGE",
    "GARBAGEMAN",
    "GARBAGEMEN",
    "GARMS",
    "GAUCHE",
    "GAUR",
    "GAURS",
    "GEAN",
    "GEANS",
    "GEAR",
    "GEARS",
    "GEG",
    "GEGS",
    "GEM",
    "GEMS",
    "GEN",
    "GENS",
    "GENA",
    "GENAE",
    "GENE",
    "GENES",
    "GENESIS",
    "GENESISES",
    "GENU",
    "GENUA",
    "GENUS",
    "GEUM",
    "GEUMS",
    "GHI",
    "GHIS",
    "GIS",
    "GIB",
    "GIBS",
    "GIBE",
    "GIE",
    "GIES",
    "GIG",
    "GIGS",
    "GNU",
    "GNUS",
    "GRAB",
    "GRABS",
    "GRABEN",
    "GRABENS",
    "GRAM",
    "GRAMS",
    "GRAN",
    "GRANS",
    "GRANA",
    "GRANUM",
    "GRANARIES",
    "GRANGE",
    "GRANGES",
    "GRAUNCH",
    "GRAUNCHES",
    "GRIG",
    "GRIGS",
    "GRUME",
    "GRUMES",
    "GRUNGE",
    "ARABIC",
    "GIRN",
    "GIRNS",
    "HEME",
    "MAI",
    "HEHE",
    "HUNG",
    "HES",
    "HEAR",
    "HEARS",
    "HEARSE",
    "HEARSES",
    "HEGIRA",
    "HEIAU",
    "HEIAUS",
    "HEIGH",
    "HEIR",
    "HEIRS",
    "HEM",
    "HEMS",
    "HEN",
    "HENS",
    "HENBANE",
    "HENBANES",
    "HENCH",
    "HENCHMAN",
    "HENCHMEN",
    "HENGE",
    "HENGES",
    "HENRIES",
    "HEUCH",
    "HEURIGE",
    "HEURIGEN",
    "HIBA",
    "HIBACHI",
    "HIBACHIS",
    "HIBISCUS",
    "HIBISCUSES",
    "HIC",
    "HIE",
    "HIES",
    "HIGH",
    "HIGHRISE",
    "HIGHRISES",
    "HIRAGANA",
    "HIS",
    "HUARACHE",
    "HUARACHES",
    "HUCHEN",
    "HUE",
    "HUES",
    "HUH",
    "HUI",
    "HUIS",
    "HUIES",
    "HUIA",
    "HUM",
    "HUMS",
    "HUMAN",
    "HUMANS",
    "HUMANE",
    "HUMUS",
    "HUN",
    "HUNCH",
    "HUNCHES",
    "IAMB",
    "IAMBS",
    "IAMBIC",
    "IAMBICS",
    "IAMBI",
    "IBIS",
    "IBISES",
    "ENURN",
    "ENURNS",
    "IRIE",
    "IRIS",
    "IRISES",
    "ISCHIUM",
    "ISCHIA",
    "ISM",
    "ISMS",
    "GIBES",
    "MABAN",
    "MABANS",
    "MAC",
    "MACS",
    "MACHE",
    "MACUMBA",
    "MAG",
    "MAGS",
    "MAGA",
    "MARGA",
    "MAGE",
    "MAGES",
    "MAGI",
    "MAGIC",
    "MAGICS",
    "MAGICIAN",
    "MAGICIANS",
    "MAGMA",
    "MAGNA",
    "MAGNESIA",
    "MAGNESIAN",
    "MAGNESIUM",
    "MAGNUM",
    "MAGNUMS",
    "MAGSMAN",
    "MAGSMEN",
    "MAM",
    "MAMS",
    "MAMA",
    "MAMBA",
    "MAN",
    "MEN",
    "MANS",
    "MANA",
    "MANAGE",
    "MANAGES",
    "MANAIA",
    "MANANA",
    "MANBAG",
    "MANBAGS",
    "MANE",
    "MANES",
    "MANEB",
    "MANEGE",
    "MANEGES",
    "MANGA",
    "MANGANESE",
    "MANGE",
    "MANGIA",
    "MANSE",
    "MANSES",
    "MANUHIRI",
    "MANUHIRIS",
    "MANUS",
    "MAR",
    "MARS",
    "MARA",
    "MARACA",
    "MARAE",
    "MARARI",
    "MARARIS",
    "MARIA",
    "MARG",
    "MARGS",
    "MARGE",
    "MARGES",
    "MARIACHI",
    "MARIACHIS",
    "MARIAGE",
    "MARIHUANA",
    "MARM",
    "MAUN",
    "MAURI",
    "MAURIS",
    "MBIRA",
    "MCS",
    "MEA",
    "MEAN",
    "MEANS",
    "MEG",
    "MEGS",
    "MEGA",
    "MEH",
    "MEMBRANE",
    "MEMBRANES",
    "MEMBRUM",
    "MEME",
    "MEMES",
    "MENAGE",
    "MENAGES",
    "MENHIR",
    "MENHIRS",
    "MENSCH",
    "MENSCHES",
    "MENSES",
    "MENS",
    "MENU",
    "MENUS",
    "MESIA",
    "MESIC",
    "MESNE",
    "MUS",
    "MUCH",
    "MUCUNA",
    "MUCUS",
    "MUM",
    "MUMS",
    "MUMSIES",
    "MUN",
    "MUNCH",
    "MUNCHES",
    "MUNCHIES",
    "MUNG",
    "MUNGS",
    "MUNGE",
    "MUNGES",
    "MURAGE",
    "MURGH",
    "MURMUR",
    "MURMURS",
    "MURU",
    "MUSCAE",
    "MUSE",
    "MUSES",
    "MUSEUM",
    "MUSEUMS",
    "MUSIC",
    "MUSICA",
    "MUSICIAN",
    "MUSICIANS",
    "NAB",
    "NABS",
    "NABE",
    "NABES",
    "NACHES",
    "NAE",
    "NAG",
    "NAGS",
    "NAGA",
    "NAGANA",
    "NAGAR",
    "NAGARS",
    "NAI",
    "NAIS",
    "NAIRA",
    "NAME",
    "NAMES",
    "NAM",
    "NAN",
    "NANS",
    "NANA",
    "NANCIES",
    "NANG",
    "NGS",
    "NARIS",
    "NAUSEA",
    "NEAR",
    "NEARS",
    "NEB",
    "NEBS",
    "NEG",
    "NEGS",
    "NEIGH",
    "NEM",
    "NEMESIA",
    "NEMESIS",
    "NEMESES",
    "NENE",
    "NENES",
    "NEUME",
    "NEUM",
    "NEUMES",
    "NEUMS",
    "NGRAM",
    "NGRAMS",
    "BENE",
    "RICHE",
    "NUS",
    "NUMB",
    "NUMBS",
    "NUMEN",
    "NUN",
    "NUNS",
    "NUNU",
    "NUNUS",
    "NURAGH",
    "NURAGHE",
    "NURAGHI",
    "NURAGHIC",
    "NURSE",
    "NURSES",
    "NURSIE",
    "NURSIES",
    "CURIAM",
    "RABI",
    "RABIES",
    "RACHIS",
    "RACISM",
    "RAG",
    "RAGS",
    "RAGA",
    "RAGE",
    "RAGES",
    "RAGI",
    "RAGMAN",
    "RAGMEN",
    "RAI",
    "RAISE",
    "RAISES",
    "RAM",
    "RAMS",
    "RAMEN",
    "RAMUS",
    "RAN",
    "RANCH",
    "RANCHES",
    "RANG",
    "RANGA",
    "RANGE",
    "RANGES",
    "RARA",
    "RAUNCH",
    "RHEA",
    "RHEME",
    "RHEMES",
    "RHESUS",
    "RHEUM",
    "RHUMB",
    "RHUMBS",
    "RIA",
    "RIB",
    "RIBS",
    "RIBCAGE",
    "RIBCAGES",
    "RICH",
    "RICHEN",
    "RICHENS",
    "RICHES",
    "RIEM",
    "RIEMS",
    "RIG",
    "RIGS",
    "RUNG",
    "RISE",
    "RISEN",
    "RISES",
    "RUA",
    "RUCHE",
    "RUCHES",
    "RUE",
    "RUES",
    "RUM",
    "RUMS",
    "RUMBA",
    "RHUMBA",
    "RUMEN",
    "RUMENS",
    "RUN",
    "RUNS",
    "RUNANGA",
    "RUNE",
    "RUNES",
    "RUNGS",
    "RUSE",
    "RUSES",
    "RUS",
    "URBE",
    "SES",
    "SCAB",
    "SCABS",
    "SCABIES",
    "SCAM",
    "SCAMS",
    "SCAN",
    "SCANS",
    "SCAR",
    "SCARS",
    "SCARAB",
    "SCARABS",
    "SCAUR",
    "SCAURS",
    "SCHEMA",
    "SCHEME",
    "SCHEMES",
    "SCHISM",
    "SCHISMS",
    "SCHMEAR",
    "SCHMEARS",
    "SCIAGRAM",
    "SCIAGRAMS",
    "SCUM",
    "SCUMS",
    "SCUMBAG",
    "SCUMBAGS",
    "SCUNGE",
    "SCUNGES",
    "SCUNGIES",
    "SEA",
    "SEABAG",
    "SEABAGS",
    "SEAM",
    "SEAMS",
    "SEAMAN",
    "SEAMEN",
    "SEAR",
    "SEARS",
    "SEGA",
    "SEI",
    "SEIS",
    "SEICHE",
    "SEICHES",
    "SEIGNEUR",
    "SEIGNEURS",
    "SEIGNEURIES",
    "SEISE",
    "SEISES",
    "SEME",
    "SEMES",
    "SEMEME",
    "SEMEMES",
    "SEMEN",
    "SEN",
    "SENARIUS",
    "SENE",
    "SENES",
    "SENSE",
    "SENSES",
    "SENSEI",
    "SENSU",
    "SENSUM",
    "CARIAMA",
    "SIAMANG",
    "SIAMANGS",
    "SIB",
    "SIBS",
    "SIBIA",
    "SIC",
    "SICS",
    "SIEGE",
    "SIEGES",
    "SIEMENS",
    "SIG",
    "SIGS",
    "SIGH",
    "SIGMA",
    "SIGN",
    "SIGNS",
    "SIGNAGE",
    "SIGNARIES",
    "SIGRI",
    "SIGRIS",
    "SUNG",
    "SIR",
    "SIRS",
    "SIS",
    "SCAG",
    "SMARM",
    "SMARMS",
    "SMEAR",
    "SMEARS",
    "SMEG",
    "SMEGMA",
    "SNAG",
    "SNAGS",
    "SNUS",
    "SUCH",
    "SUE",
    "SUES",
    "SUH",
    "SUI",
    "SUM",
    "SUMS",
    "SUMAC",
    "SUMACH",
    "SUMACS",
    "SUN",
    "SUNS",
    "SUNBEAM",
    "SUNBEAMS",
    "SUNRISE",
    "SUNRISES",
    "SUNSIGN",
    "SUNSIGNS",
    "SURA",
    "SURGE",
    "SURGES",
    "SURNAME",
    "SURNAMES",
    "SUS",
    "UHUH",
    "UMBRA",
    "UMBRAE",
    "UMBRAGE",
    "UME",
    "UMU",
    "UMUS",
    "UNAGI",
    "UNARM",
    "UNARMS",
    "UNBAN",
    "UNBANS",
    "UNBAR",
    "UNBARS",
    "UNCAGE",
    "UNCAGES",
    "UNHUNG",
    "UNHUMAN",
    "UNRIG",
    "UNRIGS",
    "UNRISEN",
    "UNSUNG",
    "URAEUS",
    "URAEI",
    "URBAN",
    "URBANE",
    "URBS",
    "URGE",
    "URGES",
    "URGENCIES",
    "URIC",
    "URN",
    "URNS",
    "URUS",
    "URUSES",
    "USE",
    "USES",
    "HUMANA",
    "CHUN",
    "BRACHIUM",
    "BRACHIUMS",
    "CARIBE",
    "CARIBES",
    "CHIA",
    "GAGMAN",
    "GAGMEN",
    "GAMBIR",
    "GENUSES",
    "GIEN",
    "GNAR",
    "GNARS",
    "EMBRUE",
    "MAGIAN",
    "MENSCHEN",
    "GAI",
    "MUNCHIE",
    "NAGE",
    "NAGES",
    "ABAC",
    "ABACS",
    "ABANGAN",
    "ABANGANS",
    "ABEAR",
    "ABEARS",
    "ABEIGH",
    "ABENG",
    "ABENGS",
    "ABHUMAN",
    "ABHUMEN",
    "ABIU",
    "ABIUS",
    "ABRI",
    "ABRIS",
    "ACARIAN",
    "ACARIANS",
    "ACARUS",
    "ACARUSES",
    "ACAUSE",
    "ACIES",
    "AGAMAE",
    "AGAMAES",
    "AGENE",
    "AGENESIC",
    "AGENESIS",
    "AGENESIA",
    "AGENESISES",
    "AGEUSIA",
    "AGEUSIC",
    "AGEUSICS",
    "AGNAME",
    "AGNAMES",
    "AGRUM",
    "AGRUMS",
    "AIE",
    "AGI",
    "AMBIGRAM",
    "AMBIGRAMS",
    "ARABA",
    "ARBA",
    "ARABAN",
    "ARABANS",
    "ARMARIAN",
    "ARMARIANS",
    "ARMBAR",
    "ARMBARS",
    "AUH",
    "AUM",
    "AUMS",
    "AUNE",
    "AUNES",
    "BENCHMAN",
    "BENCHMEN",
    "BIRSE",
    "BEUN",
    "BRUNCHIE",
    "BRUNCHIES",
    "CANANGA",
    "CANARIUM",
    "CANARIUMS",
    "CARBARN",
    "CARBARNS",
    "CHIBA",
    "CHEBA",
    "CUNEUS",
    "CUNEUSES",
    "CUSUM",
    "CUSUMS",
    "EBENE",
    "EBENA",
    "GAMB",
    "GAMBS",
    "GAMENE",
    "GAMENES",
    "GANGMAN",
    "GANGMEN",
    "GANGSMAN",
    "GANGSMEN",
    "GENESIC",
    "GRANBAIRN",
    "GRANAM",
    "HEURISM",
    "HEURISMS",
    "MAB",
    "MABE",
    "MABES",
    "MACANA",
    "MACARISM",
    "MACARISMS",
    "MACARISE",
    "MACA",
    "MAGNESIC",
    "MAIRIE",
    "MAIRIES",
    "MAISE",
    "MAISES",
    "MANACA",
    "MANCHE",
    "MANCHES",
    "MANCIA",
    "MANCUS",
    "MANCUSES",
    "MANEABA",
    "MANEH",
    "MANG",
    "MANGS",
    "MANGANESIAN",
    "MANGI",
    "MANGEMANGE",
    "MUNGAMUNGA",
    "MANGHIR",
    "MANGHIRS",
    "MAUMAU",
    "MARABI",
    "MARABA",
    "MARABIS",
    "MARAGE",
    "MARAGES",
    "MARAN",
    "MARANS",
    "MARARA",
    "MARGARIC",
    "MARIGRAM",
    "MARIGRAMS",
    "MARMA",
    "MARMEM",
    "MARMEMS",
    "MARUA",
    "MARUMAGE",
    "MAUM",
    "MAUMS",
    "MAUNCH",
    "MAUNCHE",
    "MAUNCHES",
    "MAGAME",
    "MBAR",
    "MBARS",
    "MBARI",
    "MBARIS",
    "MEISIE",
    "MEISIES",
    "MEISM",
    "MENEHUNE",
    "MENEHUNES",
    "MENSE",
    "MENSUR",
    "MENSURS",
    "MESC",
    "MESCA",
    "MESE",
    "MESES",
    "MESEM",
    "MESEMB",
    "MESEMS",
    "MESIAN",
    "MEU",
    "MEUS",
    "MEUM",
    "MEUMS",
    "MGANGA",
    "MUHR",
    "MUI",
    "MARABARABA",
    "MUCIGEN",
    "MUCIGENS",
    "MUNGA",
    "MUMESIC",
    "MUNGI",
    "MURA",
    "MURAENA",
    "MURGI",
    "MURGHI",
    "MURGIS",
    "MURUMURU",
    "MURUNGA",
    "MUSCARI",
    "MUSCARIS",
    "MUSEAU",
    "NABAM",
    "NABISM",
    "NABISMS",
    "NAGARA",
    "NAGSMAN",
    "NAGSMEN",
    "NAIB",
    "NAIBS",
    "NAR",
    "NARANGIES",
    "NARA",
    "NAUMACHIA",
    "NEBRIS",
    "NEBRISES",
    "NEGARA",
    "NEGRI",
    "NEMA",
    "NEMBIE",
    "NEMBIES",
    "NEMESISM",
    "NEMESISMS",
    "NEU",
    "NGARARA",
    "NGEGE",
    "NGEGES",
    "NUH",
    "NUNCIUS",
    "NUNCIUSES",
    "NUSE",
    "NUSES",
    "RAB",
    "RABS",
    "RABIC",
    "RACHE",
    "RACHES",
    "RACHISCHISIS",
    "RACHISCHISISES",
    "RAMAGE",
    "RAMAGES",
    "RAMARAMA",
    "RAMBAI",
    "RAMBEH",
    "RAMBAIS",
    "RAME",
    "RAMES",
    "RAMESES",
    "RAMSE",
    "RANA",
    "RANARIAN",
    "RANARIUM",
    "RANARIUMS",
    "RANSE",
    "RANCHMAN",
    "RANCHMEN",
    "RANE",
    "RAEN",
    "RANES",
    "RAUN",
    "RAIS",
    "RHE",
    "RHES",
    "RHESIS",
    "RHESISES",
    "RHUS",
    "RHUSES",
    "RIANCIES",
    "RIBES",
    "RIBESES",
    "RUACH",
    "RUACHES",
    "RUANA",
    "RUNCH",
    "RUNCHES",
    "RUNCHIE",
    "RUNGIE",
    "RUNCHIES",
    "RUNRIG",
    "RUNRIGS",
    "RURBAN",
    "RURU",
    "RURUS",
    "RUSCUS",
    "RUSCUSES",
    "RUSMA",
    "RHUSMA",
    "SCIAENA",
    "SEMA",
    "SENSI",
    "SENSIE",
    "SENSIS",
    "SENSISM",
    "SENSISMS",
    "SIGNUM",
    "SIGNUMS",
    "SUNGEM",
    "SUNGEMS",
    "UNRICH",
    "UNRANG",
    "UNRUNG",
    "URANAGE",
    "URB",
    "USEN",
    "USENS"
  ],
  "par": 4,
  "yesterdaysSolution": [
    "OXLIP",
    "PARACHUTE"
  ],
  "yesterdaysSides": [
    "EXA",
    "IUC",
    "PHO",
    "LTR"
  ],
  "isFree": false,
  "editor": "Sam Ezersky",
  "editorImage": "https://storage.googleapis.com/nyt-games-prd.appspot.com/avatars/sam-ezersky.png"
}