{
  "id": 1708,
  "expiration": 1691910000,
  "ourSolution": [
    "PORTRAYAL",
    "LONGBOWS"
  ],
  "printDate": "2023-08-12",
  "sides": [
    "PYN",
    "TLB",
    "OAS",
    "RWG"
  ],
  "date": "August 12, 2023",
  "dictionary": [
    "ABS",
    "ABAYA",
    "ABORAL",
    "ABORT",
    "ABORTS",
    "ABROGATOR",
    "ABROGATORS",
    "AGA",
    "AGAL",
    "AGALS",
    "AGAR",
    "AGLOW",
    "AGO",
    "AGOG",
    "AGOGO",
    "AGORA",
    "AGOROT",
    "ALAP",
    "ALAPS",
    "ALAR",
    "ALGA",
    "ALGAL",
    "ALGO",
    "ALGOLOGY",
    "ALONG",
    "ALOW",
    "ALP",
    "ALPS",
    "ALWAY",
    "ALWAYS",
    "ANA",
    "ANAL",
    "ANALOG",
    "ANALOGS",
    "ANALOGY",
    "ANALYST",
    "ANALYSTS",
    "ANGARY",
    "ANGORA",
    "ANGST",
    "ANGSTY",
    "ANON",
    "ANT",
    "ANTS",
    "ANTRA",
    "ANTRAL",
    "ANTSY",
    "APART",
    "APLANAT",
    "APLANATS",
    "APOLAR",
    "APOLOGY",
    "APOLS",
    "APRON",
    "APRONS",
    "APT",
    "APTS",
    "ARB",
    "ARBS",
    "ARBOR",
    "ARBORS",
    "ART",
    "ARTS",
    "ARTY",
    "ARTSY",
    "ARYL",
    "ATS",
    "ATONAL",
    "ATOP",
    "ATAP",
    "LANG",
    "AWAY",
    "AWAYS",
    "AWL",
    "AWLS",
    "AWN",
    "AWNS",
    "AYS",
    "BAB",
    "BABS",
    "BABA",
    "BABY",
    "WORST",
    "BAG",
    "BAGS",
    "BAGSY",
    "BALATA",
    "BAL",
    "BALOT",
    "BALOTS",
    "BAN",
    "BANS",
    "BANAL",
    "BANANA",
    "BANG",
    "BANGS",
    "BANGARANG",
    "BANGARANGS",
    "BANTS",
    "BAP",
    "BAPS",
    "BAR",
    "BARS",
    "BARA",
    "BARB",
    "BARBS",
    "BARBOLA",
    "BARN",
    "BARNS",
    "BARON",
    "BARONS",
    "BARTON",
    "BARTONS",
    "BARYON",
    "BARYONS",
    "BARYTA",
    "BARYTON",
    "BARYTONS",
    "BAT",
    "BATS",
    "BATATA",
    "BATON",
    "BATONS",
    "BAWL",
    "BAWLS",
    "BAWN",
    "BAWNS",
    "BAY",
    "BAYS",
    "BAYA",
    "BOB",
    "BOBS",
    "BOBA",
    "BOBOL",
    "BOBOLS",
    "BOBSTAY",
    "BOBSTAYS",
    "BOG",
    "BOGS",
    "BOGAN",
    "BOGANS",
    "BOGART",
    "BOGARTS",
    "BOGY",
    "BOGONG",
    "BOGONGS",
    "BOLAR",
    "BOLARS",
    "BOLO",
    "BOLOGNA",
    "BONA",
    "BON",
    "BONBON",
    "BONBONS",
    "BONG",
    "BONGS",
    "BONGO",
    "BONOBO",
    "BOP",
    "BOPS",
    "BORA",
    "BORN",
    "BORON",
    "BORSTAL",
    "BORSTALS",
    "BORT",
    "BOT",
    "BOTS",
    "BOTO",
    "BOW",
    "BOWS",
    "BOWL",
    "BOWLS",
    "BOWYANG",
    "BOWYANGS",
    "BOY",
    "BOYS",
    "BOYAR",
    "BOYARS",
    "BOYLYA",
    "BOYO",
    "BOYTOY",
    "BOYTOYS",
    "BRA",
    "BRAG",
    "BRAGS",
    "BRAN",
    "BRANT",
    "BRANTS",
    "BRAT",
    "BRATS",
    "BRAW",
    "BRAWLY",
    "BRAWL",
    "BRAWLS",
    "BRAWN",
    "BRAY",
    "BRAYS",
    "BRO",
    "BROGAN",
    "BROGANS",
    "BROLGA",
    "BROW",
    "BROWS",
    "BROWN",
    "BROWNS",
    "BROWNBAG",
    "BROWNBAGS",
    "BROWNTOP",
    "BROWNTOPS",
    "BRYOLOGY",
    "BWANA",
    "BYLAW",
    "BYLAWS",
    "BYWAY",
    "BYWAYS",
    "TOWN",
    "TROP",
    "NON",
    "YONG",
    "GAB",
    "GABS",
    "GAG",
    "GAGS",
    "GAGA",
    "GAL",
    "GALS",
    "GALA",
    "GALAGO",
    "GALANGAL",
    "GALANT",
    "GALOP",
    "GALOPS",
    "GALPAL",
    "GALPALS",
    "GANG",
    "GANGS",
    "GANGBANG",
    "GANGBANGS",
    "GANGLY",
    "GANGSTA",
    "GANTRY",
    "GAP",
    "GAPS",
    "GAR",
    "GARS",
    "GARB",
    "GARBS",
    "GARBA",
    "GARBO",
    "GARBOLOGY",
    "GAT",
    "GATS",
    "GATOR",
    "GATORS",
    "GAWP",
    "GAWPS",
    "GAY",
    "GAYS",
    "GAYAL",
    "GAYALS",
    "GOT",
    "GLANS",
    "GLARY",
    "GLOB",
    "GLOBS",
    "GLOBAL",
    "GLOP",
    "GLOPS",
    "GLORY",
    "GLOW",
    "GLOWS",
    "GLOWY",
    "GNARL",
    "GNARLS",
    "GNARLY",
    "GNAT",
    "GNATS",
    "GNAW",
    "GNAWS",
    "GOB",
    "GOBS",
    "GOBAR",
    "GOBO",
    "GOBY",
    "GOGO",
    "GONG",
    "GONGS",
    "GORA",
    "GORAY",
    "GORAL",
    "GORALS",
    "GORB",
    "GORBS",
    "GORP",
    "GORSY",
    "GORY",
    "GOWAN",
    "GOWANS",
    "GOWN",
    "GOWNS",
    "GOY",
    "GOYS",
    "GYAN",
    "GYRAL",
    "GYRATOR",
    "GYRATORS",
    "GYRATORY",
    "GYRO",
    "GYRON",
    "GYRONS",
    "TOTO",
    "LAB",
    "LABS",
    "LABORATORY",
    "LABOR",
    "LABORS",
    "LABRA",
    "LABRAT",
    "LABRATS",
    "LABRAL",
    "LAG",
    "LAGS",
    "LAGAN",
    "LAGAR",
    "LANGAR",
    "LANGARS",
    "LANTANA",
    "LAP",
    "LAPS",
    "LAPA",
    "LAPTOP",
    "LAPTOPS",
    "LAR",
    "LARS",
    "LARN",
    "LARNS",
    "LAT",
    "LATS",
    "LAW",
    "LAWS",
    "LAWN",
    "LAWNS",
    "LAY",
    "LAYS",
    "LAYAWAY",
    "LAYAWAYS",
    "LAYBY",
    "LAYBYS",
    "ROGATORY",
    "LOB",
    "LOBS",
    "LOBAR",
    "LOBO",
    "LOBOLA",
    "LOBOLO",
    "LOG",
    "LOGS",
    "LOGAN",
    "LOGANS",
    "LOGON",
    "LOGONS",
    "LOGO",
    "LOGY",
    "LOL",
    "LOLS",
    "LONG",
    "LONGS",
    "LONGA",
    "LONGAN",
    "LONGANS",
    "LONGBOW",
    "LONGBOWS",
    "LONGSTOP",
    "LONGSTOPS",
    "LOP",
    "LOPS",
    "LOR",
    "LORN",
    "LORY",
    "LOT",
    "LOTS",
    "LOTA",
    "LOW",
    "LOWS",
    "LOWAN",
    "LOWANS",
    "LOWBORN",
    "LOWBOY",
    "LOWBOYS",
    "LOWBROW",
    "LOWBROWS",
    "LOWLY",
    "LOYAL",
    "NAB",
    "NABS",
    "NABOB",
    "NABOBS",
    "NAG",
    "NAGS",
    "NAGA",
    "NAGANA",
    "NAGAR",
    "NAGARS",
    "NAN",
    "NANS",
    "NANA",
    "NANG",
    "NANO",
    "NANOBOT",
    "NANOBOTS",
    "NGS",
    "NANOROBOT",
    "NANOROBOTS",
    "NANTO",
    "NAP",
    "NAPS",
    "NAPA",
    "NARY",
    "NATAL",
    "NATANT",
    "NATATORY",
    "NATRON",
    "NAW",
    "NAWAB",
    "NAWABS",
    "NAY",
    "NAYS",
    "OBSTAT",
    "NOB",
    "NOBS",
    "NOG",
    "NOGS",
    "NOGAL",
    "NOLO",
    "NONAGON",
    "NONAGONS",
    "NONAGONAL",
    "NONAPOLOGY",
    "NONARY",
    "NONG",
    "NONGS",
    "NONSTOP",
    "NOPAL",
    "NOR",
    "NORS",
    "NOT",
    "NOTS",
    "NOTARY",
    "NOTATOR",
    "NOTATORS",
    "NOTA",
    "NOTAL",
    "NOW",
    "NOWAY",
    "NOWAYS",
    "NOWT",
    "NALA",
    "OBA",
    "OBOL",
    "OBOLS",
    "OLOGY",
    "ONLY",
    "ONTO",
    "ONTOLOGY",
    "OPS",
    "OPAL",
    "OPALS",
    "OPT",
    "OPTS",
    "OPTANT",
    "OPTANTS",
    "ORS",
    "ORA",
    "ORAL",
    "ORALS",
    "ORANG",
    "ORANGS",
    "ORANGY",
    "ORATOR",
    "ORATORS",
    "ORATORY",
    "ORB",
    "ORBS",
    "ORBAT",
    "ORLOP",
    "ORLOPS",
    "ORT",
    "ORTS",
    "ORTOLAN",
    "ORTOLANS",
    "OTOLOGY",
    "OWL",
    "OWLS",
    "OWN",
    "OWNS",
    "OWT",
    "PAN",
    "PANS",
    "PAGAN",
    "PAGANS",
    "PAL",
    "PALS",
    "PALAPA",
    "PALATAL",
    "PALATALS",
    "PALAY",
    "PALOLO",
    "PALP",
    "PALPS",
    "PALPAL",
    "PALSY",
    "PALY",
    "PANG",
    "PANGS",
    "PANGA",
    "PANOPLY",
    "PANSY",
    "PANT",
    "PANTS",
    "PANTY",
    "PANTO",
    "PANTRY",
    "PAP",
    "PAPS",
    "PAPA",
    "PAPAL",
    "PAPAYA",
    "PAR",
    "PARS",
    "PARA",
    "PARABOLA",
    "PARAGON",
    "PARAGONS",
    "PARALOGY",
    "PARANG",
    "PARANGS",
    "PARLAY",
    "PARLAYS",
    "PARLOR",
    "PARLORS",
    "PAROL",
    "PARP",
    "PARPS",
    "PART",
    "PARTS",
    "PARTWAY",
    "PARTY",
    "PAT",
    "PATS",
    "PATROL",
    "PATROLS",
    "PATROLOGY",
    "PATRON",
    "PATRONS",
    "PATRONAL",
    "PATSY",
    "PAW",
    "PAWS",
    "PAWANG",
    "PAWANGS",
    "PAWL",
    "PAWLS",
    "PAWN",
    "PAWNS",
    "PAWPAW",
    "PAPAW",
    "PAWPAWS",
    "PAPAWS",
    "PAY",
    "PAYS",
    "PAYOLA",
    "PLAGAL",
    "PLAN",
    "PLANS",
    "PLANAR",
    "PLANT",
    "PLANTS",
    "PLANTAR",
    "PLAT",
    "PLATS",
    "PLATAN",
    "PLATANS",
    "PLATY",
    "PLAY",
    "PLAYS",
    "PLAYA",
    "PLAYBOY",
    "PLAYBOYS",
    "PLOP",
    "PLOPS",
    "PLOT",
    "PLOTS",
    "PLOW",
    "PLOWS",
    "PLOY",
    "PLOYS",
    "PLS",
    "PLY",
    "POBOY",
    "POGO",
    "POL",
    "POLS",
    "POLAR",
    "POLARS",
    "POLO",
    "POLY",
    "POLYS",
    "POLYBAG",
    "POLYBAGS",
    "POLYGLOT",
    "POLYGLOTS",
    "POLYGLOTAL",
    "POLYGON",
    "POLYGONS",
    "POLYGONAL",
    "POLYTONAL",
    "PONG",
    "PONGS",
    "PONGY",
    "PONGA",
    "PONGAL",
    "PONGALS",
    "PONGO",
    "PONS",
    "PONT",
    "PONTS",
    "POP",
    "POPS",
    "POPLAR",
    "POPLARS",
    "POPO",
    "POPSTAR",
    "POPSTARS",
    "POPSY",
    "PORN",
    "PORNO",
    "PORT",
    "PORTS",
    "PORTAL",
    "PORTALS",
    "PORTOLAN",
    "PORTOLANO",
    "PORTOLANS",
    "PORTRAY",
    "PORTRAYS",
    "PORTRAYAL",
    "PORTRAYALS",
    "POT",
    "POTS",
    "POTATORY",
    "POTATO",
    "POTPLANT",
    "POTPLANTS",
    "POW",
    "POWAN",
    "POWANS",
    "PRANA",
    "PRANG",
    "PRANGS",
    "PRAT",
    "PRATS",
    "PRAWN",
    "PRAWNS",
    "PRAY",
    "PRAYS",
    "PRO",
    "PROB",
    "PROBS",
    "PROBANG",
    "PROBANGS",
    "PROBY",
    "BONO",
    "PROG",
    "PROGS",
    "PROLONG",
    "PROLONGS",
    "PRONATOR",
    "PRONATORS",
    "PRONG",
    "PRONGS",
    "PRONTO",
    "PROP",
    "PROPS",
    "PROPAGATOR",
    "PROPAGATORS",
    "PROPANOL",
    "PROPRANOLOL",
    "PROTON",
    "PROTONS",
    "PROTONOTARY",
    "PROW",
    "PROWS",
    "PROWL",
    "PROWLS",
    "PRY",
    "PSYOPS",
    "PSYWAR",
    "PWN",
    "PWNS",
    "RABONA",
    "RAG",
    "RAGS",
    "RAGA",
    "RAGBAG",
    "RAGBAGS",
    "RAGLAN",
    "RAGLANS",
    "RAGTAG",
    "RAGTOP",
    "RAGTOPS",
    "RAN",
    "RANG",
    "RANGA",
    "RANGY",
    "RANT",
    "RANTS",
    "RAP",
    "RAPS",
    "RAPT",
    "RAPTOR",
    "RAPTORS",
    "RARA",
    "RAT",
    "RATS",
    "RATA",
    "RATAPLAN",
    "RATATAT",
    "RATATATS",
    "RAW",
    "RAWLY",
    "RAY",
    "RAYS",
    "RAYON",
    "RABATO",
    "ROB",
    "ROBS",
    "ROBATA",
    "ROBORANT",
    "ROBORANTS",
    "ROBOT",
    "ROBOTS",
    "ROGAN",
    "RONGORONGO",
    "RORT",
    "RORTS",
    "RORTY",
    "ROT",
    "ROTS",
    "ROTA",
    "ROTARY",
    "ROTATORY",
    "ROTATOR",
    "ROTATORS",
    "ROTOR",
    "ROTORS",
    "ROW",
    "ROWS",
    "ROWAN",
    "ROWANS",
    "ROYAL",
    "ROYALS",
    "RYOT",
    "RYOTS",
    "LATO",
    "SLAB",
    "SLABS",
    "SLAG",
    "SLAGS",
    "SLANG",
    "SLANGS",
    "SLANGY",
    "SLANT",
    "SLANTS",
    "SLAP",
    "SLAPS",
    "SLAT",
    "SLATS",
    "SLATY",
    "SLAW",
    "SLAY",
    "SLAYS",
    "SLOB",
    "SLOBS",
    "SLOG",
    "SLOGS",
    "SLOGAN",
    "SLOGANS",
    "SLOP",
    "SLOPS",
    "SLOT",
    "SLOTS",
    "SLOW",
    "SLOWS",
    "SLOWLY",
    "SLY",
    "SLYLY",
    "SNAG",
    "SNAGS",
    "SNAP",
    "SNAPS",
    "SNARL",
    "SNARLS",
    "SNARLY",
    "SNOB",
    "SNOBS",
    "SNOG",
    "SNOGS",
    "SNORT",
    "SNORTS",
    "SNOT",
    "SNOTS",
    "SNOW",
    "SNOWS",
    "SNOWPANTS",
    "SNOWPANT",
    "SNOWPLOW",
    "SNOWPLOWS",
    "SNOWY",
    "SPA",
    "SPAG",
    "BOL",
    "SPAN",
    "SPANS",
    "SPANG",
    "SPANGLY",
    "SPAR",
    "SPARS",
    "SPARTAN",
    "SPARTANLY",
    "SPAT",
    "SPATS",
    "SPAWN",
    "SPAWNS",
    "SPAY",
    "SPAYS",
    "SPLAT",
    "SPLATS",
    "SPLAY",
    "SPLAYS",
    "SPONGY",
    "SPORT",
    "SPORTS",
    "SPORTY",
    "SPOT",
    "SPOTS",
    "SPRAG",
    "SPRAGS",
    "SPRANG",
    "SPRAT",
    "SPRATS",
    "SPRAWL",
    "SPRAWLS",
    "SPRAY",
    "SPRAYS",
    "SPROG",
    "SPROGS",
    "SPRY",
    "SPRYLY",
    "SRSLY",
    "STAB",
    "STABS",
    "STAG",
    "STAGS",
    "STAGNANT",
    "STAGY",
    "STALWART",
    "STALWARTS",
    "STAN",
    "STANS",
    "STAR",
    "STARS",
    "START",
    "STARTS",
    "STAT",
    "STATANT",
    "STATOR",
    "STATORS",
    "STATS",
    "STAY",
    "STAYS",
    "STOB",
    "STOBS",
    "STOG",
    "STOGS",
    "STOGY",
    "STOLON",
    "STOLONS",
    "STOP",
    "STOPS",
    "STOPGAP",
    "STOPGAPS",
    "STORY",
    "STOT",
    "STOTS",
    "STOW",
    "STOWS",
    "STOWAWAY",
    "STOWAWAYS",
    "STRAP",
    "STRAPS",
    "STRAPON",
    "STRATA",
    "STRATAL",
    "STRAW",
    "STRAWS",
    "STRAWY",
    "STRAY",
    "STRAYS",
    "STRONG",
    "STRONGLY",
    "STROP",
    "STROPS",
    "STROW",
    "STROWN",
    "STROWS",
    "STY",
    "STYLAR",
    "STYLO",
    "STYLOPS",
    "SWAB",
    "SWABS",
    "SWOB",
    "SWOBS",
    "SWAG",
    "SWAGS",
    "SWAN",
    "SWANS",
    "SWAP",
    "SWOP",
    "SWAPS",
    "SWOPS",
    "SWART",
    "SWAT",
    "SWATS",
    "SWAY",
    "SWAYS",
    "SWORN",
    "SWOT",
    "SWOTS",
    "SWY",
    "TAB",
    "TABS",
    "TABOR",
    "TABORS",
    "TAG",
    "TAGS",
    "TAL",
    "TALS",
    "TALA",
    "TALON",
    "TALONS",
    "TALWAR",
    "TALWARS",
    "TAN",
    "TANS",
    "TANG",
    "TANGS",
    "TANGA",
    "TANGATA",
    "TANGLY",
    "TANGO",
    "TANGY",
    "TANSY",
    "TANT",
    "TANTO",
    "TANTRA",
    "TAP",
    "TAPS",
    "TAPA",
    "TAR",
    "TARS",
    "TARA",
    "TARATA",
    "TARBOY",
    "TARBOYS",
    "TARLATAN",
    "TARLATANS",
    "TARN",
    "TARNS",
    "TARO",
    "TAROT",
    "TAROTS",
    "TARP",
    "TARPS",
    "TARPAN",
    "TARPANS",
    "TARPON",
    "TARPONS",
    "TART",
    "TARTS",
    "TARTAN",
    "TARTANS",
    "TARTAR",
    "TARTARS",
    "TARTY",
    "TAT",
    "TATS",
    "TATA",
    "TAW",
    "TAWS",
    "TAWA",
    "TAYRA",
    "TORN",
    "TSPS",
    "TOBY",
    "TOG",
    "TOGS",
    "TOGA",
    "TOGT",
    "TOLAR",
    "TOLARS",
    "TON",
    "TONS",
    "TNS",
    "TONAL",
    "TONG",
    "TONGS",
    "TONGA",
    "TOP",
    "TOPS",
    "TOPO",
    "TOPOLOGY",
    "TOR",
    "TORS",
    "TORO",
    "TORPOR",
    "TORT",
    "TORTS",
    "TORTA",
    "TOT",
    "TOTS",
    "TOTAL",
    "TOTALS",
    "TOTARA",
    "TOTY",
    "TOW",
    "TOWS",
    "TOWY",
    "TOWBAR",
    "TOWBARS",
    "TOWNS",
    "TOY",
    "TOYS",
    "TOYBOY",
    "TOYBOYS",
    "TOYON",
    "TOYONS",
    "TOYTOWN",
    "TRAGOPAN",
    "TRAGOPANS",
    "TRA",
    "TRANS",
    "TRANSGLOBAL",
    "TRANSLATOR",
    "TRANSLATORS",
    "TRANSPLANT",
    "TRANSPLANTS",
    "TRANSPORT",
    "TRANSPORTS",
    "TRAP",
    "TRAPS",
    "TRAPO",
    "TRAWL",
    "TRAWLS",
    "TRAY",
    "TRAYS",
    "TRAYTOP",
    "TRAYTOPS",
    "TROG",
    "TROGS",
    "TROGON",
    "TROGONS",
    "TRONA",
    "TROPOLOGY",
    "TROT",
    "TROTS",
    "TROW",
    "TROWS",
    "TROY",
    "TROYS",
    "TRY",
    "TRYST",
    "TRYSTS",
    "TWANG",
    "TWANGS",
    "TWANGY",
    "TWO",
    "TYRANT",
    "TYRANTS",
    "TYRO",
    "BATO",
    "WAG",
    "WAGS",
    "WAGON",
    "WAGONS",
    "WAWA",
    "WAN",
    "WANLY",
    "WANT",
    "WANTS",
    "WANTAWAY",
    "WANTON",
    "WANTONS",
    "WANTONLY",
    "WAR",
    "WARS",
    "WARBY",
    "WARN",
    "WARNS",
    "WARP",
    "WARPS",
    "WART",
    "WARTS",
    "WARTY",
    "WARY",
    "WAT",
    "WATS",
    "WAY",
    "WAYS",
    "WAYANG",
    "WAYANGS",
    "WAYLAY",
    "WAYLAYS",
    "WORN",
    "WON",
    "WOT",
    "WONGA",
    "WONT",
    "WONTS",
    "WONTON",
    "WONTONS",
    "WOP",
    "WOPS",
    "WORS",
    "WORSTS",
    "WORT",
    "WORTS",
    "WOW",
    "WOWS",
    "WPB",
    "YAG",
    "YAGS",
    "YAGNA",
    "YANG",
    "YANTRA",
    "YAP",
    "YAPS",
    "YARN",
    "YARNS",
    "YATRA",
    "YAW",
    "YAWS",
    "YAWL",
    "YAWLS",
    "YAWN",
    "YAWNS",
    "YAWP",
    "YAWPS",
    "YAY",
    "YOB",
    "YOBS",
    "YOGA",
    "YON",
    "YOW",
    "YOWL",
    "YOWLS",
    "YOYO",
    "BOLA",
    "GANGPLOW",
    "GANGPLOWS",
    "GNAR",
    "GNARS",
    "LORAN",
    "NONART",
    "OYS",
    "TSP",
    "WAYWORN",
    "ABANGAN",
    "ABANGANS",
    "ABATON",
    "ABATONS",
    "ABATOR",
    "ABATORS",
    "ABOB",
    "ABORN",
    "ABORNS",
    "ABY",
    "AGATY",
    "AGBA",
    "AGY",
    "AGON",
    "AGONS",
    "AGONAL",
    "AGONALS",
    "ALALA",
    "ALARY",
    "ALATA",
    "ALAN",
    "ALGAROT",
    "ALOP",
    "ANALOGON",
    "ANALOGONS",
    "ANTA",
    "ANTAGONAL",
    "ANTAPOLOGY",
    "ARABA",
    "ARBA",
    "ARABAN",
    "ARABANS",
    "ARTOLATRY",
    "BALON",
    "BALONS",
    "BARANGAY",
    "BARANGAYS",
    "BARONG",
    "BARONGS",
    "BOTA",
    "BOTANOLOGY",
    "BOYLY",
    "BOYSY",
    "BROWST",
    "BROWSTS",
    "BROWSY",
    "GALANGA",
    "GARBAGY",
    "GARBARATOR",
    "GAYATRY",
    "GLOBY",
    "GOBANG",
    "GOBAN",
    "LABORANT",
    "LABORANTS",
    "LABRYS",
    "LAWSY",
    "LAGO",
    "LOLA",
    "LOLO",
    "LONGLY",
    "LOTONG",
    "LOTONGS",
    "LOWN",
    "LOWNS",
    "LOWT",
    "LOWY",
    "NABY",
    "NAGARA",
    "NAWAL",
    "NANT",
    "NANTS",
    "NANTY",
    "NAR",
    "NARANGY",
    "NARA",
    "NATYA",
    "NGARARA",
    "NOPA",
    "NOPO",
    "NONAN",
    "NONANOYL",
    "NONANOYLS",
    "NOY",
    "NOWP",
    "NORY",
    "NOWN",
    "NAWN",
    "NOWY",
    "NOYS",
    "NRTYA",
    "OBO",
    "OBOY",
    "OBSTANT",
    "OGA",
    "OGO",
    "OGOGORO",
    "OLA",
    "OLONA",
    "ONGON",
    "ONGONS",
    "ONLAP",
    "ONLAPS",
    "ONLAY",
    "ONLAYS",
    "ONOLATRY",
    "ONTAL",
    "OPA",
    "OPRY",
    "OPTO",
    "ORANS",
    "ORANT",
    "ORL",
    "OROLOGY",
    "ORP",
    "ORPS",
    "OTARY",
    "WABAYO",
    "OWLY",
    "PAGANLY",
    "PAGANRY",
    "PALA",
    "PALABRA",
    "PALANG",
    "PALANGS",
    "PALAR",
    "PALPATORY",
    "PALPON",
    "PALPONS",
    "PALSYWORT",
    "PALSYWORTS",
    "PANARY",
    "PANORAL",
    "PANTAN",
    "PANTANS",
    "PANTOLOGY",
    "PANTONAL",
    "PANTOYL",
    "PANTOYLS",
    "PAPOLATRY",
    "PARALOG",
    "PARALOGS",
    "PARANATAL",
    "PARANOTAL",
    "PARAPATRY",
    "PARAPOLAR",
    "PARATONAL",
    "PARLATORY",
    "PARLY",
    "PARORAL",
    "PARTAN",
    "PARTANS",
    "PATA",
    "PATAGON",
    "PATANA",
    "PATOLA",
    "PATROLATRY",
    "PATRONAT",
    "PATRONATS",
    "PATRONLY",
    "PAWNOR",
    "PAWNORS",
    "PAYBOB",
    "PAYBOBS",
    "PAYOR",
    "PAYORS",
    "PLAGA",
    "PLANARY",
    "PLANONT",
    "PLANONTS",
    "PLAP",
    "PLAPS",
    "PLATANO",
    "PLAYWAY",
    "PLAYWAYS",
    "PLOWT",
    "POBS",
    "POGONOLOGY",
    "POG",
    "POGY",
    "POLARLY",
    "POLARON",
    "POLARONS",
    "POLYGAR",
    "POLOLOGY",
    "POLONGA",
    "POLYABOLO",
    "POLYGALA",
    "POLYLOGY",
    "POLYOL",
    "POLYOLS",
    "POLYSPORY",
    "POLYSTYROL",
    "POLYSTYROLS",
    "POLYTOPAL",
    "PONOR",
    "PONORS",
    "PONTAL",
    "PORAL",
    "POROPORO",
    "PORTY",
    "PORY",
    "POTATOR",
    "POTATORS",
    "POTRO",
    "POTSY",
    "POWSY",
    "POYA",
    "PRAG",
    "PRAGS",
    "PRALAYA",
    "PRALAY",
    "PRAPS",
    "PRATAL",
    "PROBATORY",
    "PROLAN",
    "PROLANS",
    "PRONOTAL",
    "PRONOTARY",
    "PROPAGANT",
    "PROPAGANTS",
    "PROPAGATORY",
    "PROPANAL",
    "PROPANALS",
    "PROPORT",
    "PROPORTS",
    "PRORA",
    "PRORAL",
    "PROROGATOR",
    "PROROGATORS",
    "PROTAGON",
    "PROTAGONS",
    "PROTAN",
    "PROTANS",
    "PROTOLOG",
    "PROTOLOGY",
    "PROTOPLOT",
    "PROTOPLOTS",
    "PROTOPOP",
    "PRYAN",
    "PRYTAN",
    "PALWAR",
    "PONTO",
    "RAB",
    "RABS",
    "RAL",
    "RALS",
    "RANA",
    "RANGANT",
    "RANTY",
    "RAPTATORY",
    "RATAL",
    "RATALS",
    "RATO",
    "RAWN",
    "RAWNS",
    "RAYA",
    "RAYL",
    "RAYLS",
    "RORY",
    "ROBALO",
    "ROBOTOLOGY",
    "ROBOTRY",
    "ROBOTY",
    "ROGNON",
    "ROGNONS",
    "ROLAG",
    "ROLAGS",
    "ROLOWAY",
    "ROLOWAYS",
    "ROTAL",
    "ROTAN",
    "ROTANG",
    "ROTANS",
    "ROTO",
    "ROTOLO",
    "ROTON",
    "ROTONS",
    "ROWN",
    "ROWNS",
    "ROYT",
    "RYA",
    "RYBAT",
    "RYBATS",
    "RYO",
    "RYOTWAR",
    "RAYATWAR",
    "RYOTWARY",
    "SLANTY",
    "STARY",
    "STARN",
    "STARNS",
    "STARSPOT",
    "STARSPOTS",
    "STARTY",
    "STATAL",
    "STATARY",
    "STATOLATRY",
    "STATOLON",
    "STATALON",
    "STATOLONS",
    "STORYOLOGY",
    "TABO",
    "TOWNO",
    "TOWNLY",
    "TOWNSBOY",
    "TOWNSBOYS",
    "TRAG",
    "TRAGS",
    "TRAGA",
    "TRAGAL",
    "TROPAL",
    "TROPAN",
    "TROPARY",
    "TROPO",
    "WANTA",
    "WANTY",
    "WANWORT",
    "YAYA",
    "YOLP",
    "YOLPS",
    "YOPO"
  ],
  "par": 5,
  "yesterdaysSolution": [
    "FRAMEWORK",
    "KNISH"
  ],
  "yesterdaysSides": [
    "HWI",
    "RSE",
    "FAK",
    "NMO"
  ],
  "isFree": false,
  "editor": "Sam Ezersky",
  "editorImage": "https://storage.googleapis.com/nyt-games-prd.appspot.com/avatars/sam-ezersky.png"
}