{
  "id": 2460,
  "expiration": 1756537200,
  "ourSolution": [
    "BUREAUCRATIZED",
    "DOJO"
  ],
  "printDate": "2025-08-29",
  "sides": [
    "UDT",
    "ZOR",
    "EJC",
    "BIA"
  ],
  "date": "August 29, 2025",
  "dictionary": [
    "ACAJOU",
    "ACARA",
    "ACARID",
    "ACARICIDE",
    "ACID",
    "ACIDIC",
    "ACIDOTIC",
    "ACRE",
    "ACRED",
    "ACRID",
    "ACT",
    "ACTED",
    "ADIEU",
    "ADIT",
    "ADJURE",
    "ADJURED",
    "ADO",
    "ADOBE",
    "ADOBO",
    "ADRET",
    "ADZE",
    "ADZ",
    "ADZED",
    "AERATE",
    "AERATED",
    "AJAR",
    "ACRATIC",
    "ARACARI",
    "ARB",
    "ARBOUR",
    "ARBOURED",
    "ARC",
    "ARCADE",
    "ARCADED",
    "ARCO",
    "ARCTIC",
    "ARCUATE",
    "ARDOUR",
    "ARE",
    "AREA",
    "ARETE",
    "ARID",
    "ART",
    "ARTIC",
    "ARTIER",
    "ATACTIC",
    "ATARACTIC",
    "ATE",
    "AURA",
    "AURAE",
    "AURAR",
    "AUREATE",
    "AUREI",
    "AURIC",
    "AZIDE",
    "AZURE",
    "AZURITE",
    "EARED",
    "BEAD",
    "BEADED",
    "BEADIER",
    "BEAR",
    "BEARCAT",
    "BEARD",
    "BEARDED",
    "BEARDIER",
    "BEARDIE",
    "BEARER",
    "BEAT",
    "BEATER",
    "BEAU",
    "BED",
    "BEDAD",
    "BEDAUB",
    "BEDAUBED",
    "BEDOURIE",
    "BEIRA",
    "BERATE",
    "BERATED",
    "BERET",
    "BET",
    "BETA",
    "BETAREADER",
    "BETE",
    "BETIDE",
    "BETIDED",
    "BOA",
    "BOAR",
    "BOARD",
    "BOARDED",
    "BOARDER",
    "BOAT",
    "BOATED",
    "BOATER",
    "BOATIE",
    "BOB",
    "BOBCAT",
    "BOBOTIE",
    "BOD",
    "BODE",
    "BODED",
    "BODIED",
    "BOER",
    "BOERIE",
    "BOITE",
    "JOUR",
    "BOART",
    "BOT",
    "BOTO",
    "BOUBOU",
    "BRA",
    "BRACT",
    "BRACTEATE",
    "BRAD",
    "BRAE",
    "BRAT",
    "BRAZE",
    "BRAZED",
    "BRAZIER",
    "BREAD",
    "BREADED",
    "BREADBOARD",
    "BREADBOARDED",
    "BREADIER",
    "BRED",
    "BREDIE",
    "BRER",
    "BRIER",
    "BRIDE",
    "BRIDETOBE",
    "BRIDIE",
    "BRIO",
    "BRUBRU",
    "BRUCITE",
    "BRUIT",
    "BRUITED",
    "BUB",
    "BUBO",
    "BUR",
    "BURB",
    "BURBOT",
    "BUREAU",
    "BUREAUCRAT",
    "BUREAUCRATIC",
    "BUREAUCRATIZE",
    "BUREAUCRATIZED",
    "BURET",
    "BURIED",
    "CACA",
    "CACAO",
    "CACTI",
    "CAD",
    "CADET",
    "CADRE",
    "CAR",
    "CARACARA",
    "CARAT",
    "CARB",
    "CARBURETED",
    "CARBURIZE",
    "CARBURIZED",
    "CARCADE",
    "CARCAJOU",
    "CARD",
    "CARDED",
    "CARDER",
    "CARDBOARD",
    "CARDIE",
    "CARDI",
    "CARDIO",
    "CARDIOID",
    "CARE",
    "CARED",
    "CARER",
    "CARET",
    "CARIOCA",
    "CART",
    "CARTED",
    "CARTER",
    "CAT",
    "CATARACT",
    "CATBOAT",
    "CATE",
    "CATER",
    "CATERED",
    "CATERER",
    "TREAD",
    "CICADA",
    "CICATRIZE",
    "CICATRIZED",
    "CIDER",
    "CIRCA",
    "CIRCUIT",
    "CIRCUITED",
    "CIRCUITBOARD",
    "CIRE",
    "CITE",
    "CITED",
    "CITRATE",
    "CITRIC",
    "COARCT",
    "COARCTED",
    "COARCTATE",
    "COAT",
    "COATED",
    "COATI",
    "COB",
    "COBRA",
    "COCA",
    "COCO",
    "COCOA",
    "COD",
    "CODA",
    "CODE",
    "CODED",
    "CODER",
    "COED",
    "COIR",
    "ARTE",
    "COT",
    "COTE",
    "COTERIE",
    "ETAT",
    "COUREUR",
    "COURIER",
    "COURIERED",
    "COURT",
    "COURTED",
    "COURTIER",
    "CRATE",
    "CRATED",
    "CRATER",
    "CRATERED",
    "CRAZE",
    "CRAZED",
    "CRAZIER",
    "CREATE",
    "CREATED",
    "CRED",
    "CREDIT",
    "CREDITED",
    "CREDO",
    "CRETIC",
    "CRICOID",
    "CRI",
    "COUR",
    "CRIED",
    "CRIER",
    "CRIT",
    "CRITIC",
    "CRITICIZE",
    "CRITICIZED",
    "CRITICIZER",
    "CRU",
    "CRUET",
    "CRURA",
    "CRUZADO",
    "CUB",
    "CUBE",
    "CUBED",
    "CUBEB",
    "CUBOID",
    "CUE",
    "CUED",
    "CUI",
    "CUR",
    "CURACAO",
    "CURACOA",
    "CURARE",
    "CURATE",
    "CURATED",
    "CURB",
    "CURBED",
    "CURD",
    "CURE",
    "CURED",
    "CURER",
    "CURIE",
    "CURIO",
    "CURT",
    "CUZ",
    "DACITE",
    "DACITIC",
    "DACOIT",
    "DAD",
    "DADA",
    "DADBOD",
    "DADO",
    "DARE",
    "DARED",
    "DARER",
    "DART",
    "DARTED",
    "DARTBOARD",
    "DARTER",
    "DAT",
    "DATA",
    "DATE",
    "DATED",
    "DATER",
    "DAUB",
    "DAUBED",
    "DAUBE",
    "DAUBER",
    "DAZE",
    "DAZED",
    "DEAD",
    "DEADER",
    "DEADBEAT",
    "DEAERATE",
    "DEAERATED",
    "DEAR",
    "DEARER",
    "DEARIE",
    "DEB",
    "DEBRIDE",
    "DEBRIDED",
    "DEBT",
    "DEBUR",
    "DEDICATE",
    "DEDICATED",
    "DICTO",
    "DEICIDE",
    "DEICTIC",
    "DEID",
    "JURE",
    "DEODAR",
    "DER",
    "DERATE",
    "DERATED",
    "DERE",
    "DERIDE",
    "DERIDED",
    "DERIDER",
    "DETER",
    "DETOUR",
    "DETOURED",
    "DETRACT",
    "DETRACTED",
    "DICIER",
    "DICOT",
    "DICTA",
    "DICTATE",
    "DICTATED",
    "DID",
    "DIDACTIC",
    "DIDI",
    "DIDICOI",
    "DIDO",
    "DIE",
    "DIED",
    "DIET",
    "DIETED",
    "DIETER",
    "DIETETIC",
    "DIODE",
    "DIRE",
    "DIRER",
    "DIRT",
    "DIRTIER",
    "DIRTIED",
    "DIT",
    "DITZ",
    "DITZIER",
    "DIURETIC",
    "DOB",
    "DOBE",
    "DOBRA",
    "DOCO",
    "DOCU",
    "DODO",
    "DOE",
    "DOER",
    "DOIT",
    "DOITED",
    "DOJO",
    "DOT",
    "DOTARD",
    "DOTE",
    "DOTED",
    "DOTER",
    "DOUBT",
    "DOUBTED",
    "DOUBTER",
    "DOUC",
    "DOUR",
    "DRAT",
    "DREAD",
    "DREADED",
    "DREAR",
    "DREARIER",
    "DRIED",
    "DRUB",
    "DRIER",
    "EAR",
    "EAT",
    "EATER",
    "EDICT",
    "EDIT",
    "EDITED",
    "EDITIO",
    "EIDER",
    "EIDETIC",
    "ERA",
    "ERADICATE",
    "ERADICATED",
    "ERE",
    "EREADER",
    "ERICA",
    "ERUCIC",
    "ERUCT",
    "ERUCTED",
    "ERUCTATE",
    "ERUCTATED",
    "ETA",
    "ETIC",
    "ETRIER",
    "EUCRITE",
    "AERIE",
    "JOIE",
    "ICTERIC",
    "ICIER",
    "IDE",
    "IDEA",
    "IDEATE",
    "IDEATED",
    "IDIOT",
    "IDIOTIC",
    "TOTO",
    "IODATE",
    "IODIC",
    "IODIDE",
    "IODIZE",
    "IODIZED",
    "IOTA",
    "IRADE",
    "IRATE",
    "IRE",
    "IRIE",
    "IRITIC",
    "ITERATE",
    "ITERATED",
    "IZARD",
    "JADE",
    "JADED",
    "JADEITE",
    "JADOUBE",
    "JAR",
    "JATI",
    "JATO",
    "JIRD",
    "JIT",
    "JOB",
    "JOE",
    "JOT",
    "JOTA",
    "JUA",
    "JUBE",
    "JUICIER",
    "JUJU",
    "JUJUBE",
    "JURAT",
    "JURIED",
    "REO",
    "OUR",
    "REA",
    "BOUE",
    "OAR",
    "OARED",
    "OAT",
    "OATIER",
    "OATER",
    "OBOE",
    "OCA",
    "OCICAT",
    "OCTAD",
    "OCTET",
    "ODE",
    "ODIC",
    "ODEA",
    "ODOUR",
    "OER",
    "CIT",
    "BUCO",
    "OTIC",
    "OUBOET",
    "CADI",
    "CARTE",
    "ERAT",
    "RACIER",
    "RAD",
    "RADAR",
    "RADIO",
    "RADIOED",
    "ETRE",
    "RAJ",
    "RAJA",
    "RARA",
    "RARE",
    "RARER",
    "RAT",
    "RATA",
    "RATATAT",
    "RATE",
    "RATED",
    "RATIO",
    "RATITE",
    "RAZE",
    "RAZED",
    "REACT",
    "REACTED",
    "READ",
    "READER",
    "READIER",
    "READIED",
    "REAR",
    "REARED",
    "REARER",
    "REBOARD",
    "REBOARDED",
    "REBURIED",
    "RED",
    "REDACT",
    "REDACTED",
    "REDCOAT",
    "REDE",
    "REDED",
    "REDEDICATE",
    "REDEDICATED",
    "REDID",
    "REDO",
    "REDOUBT",
    "REITERATE",
    "REITERATED",
    "RERATE",
    "RERATED",
    "REREAD",
    "RET",
    "RETARD",
    "RETARDED",
    "RETARDER",
    "RETARDATE",
    "RETE",
    "RETIE",
    "RETIED",
    "RETIRE",
    "RETIRED",
    "RETIRER",
    "RETRACT",
    "RETRACTED",
    "RETREAD",
    "RETREADED",
    "RETREAT",
    "RETREATED",
    "RETRIED",
    "REZ",
    "RICRAC",
    "RID",
    "RIDE",
    "RIDER",
    "RIDIC",
    "RIOT",
    "RIOTED",
    "RIOTER",
    "RITE",
    "RITZ",
    "RITZIER",
    "RUA",
    "RUB",
    "RUBE",
    "RUBRIC",
    "RUBRICATE",
    "RUBRICATED",
    "RUE",
    "RUED",
    "URBE",
    "TACIT",
    "TACO",
    "TACT",
    "TACTIC",
    "TAD",
    "TADA",
    "TAE",
    "TAJ",
    "TAR",
    "TARA",
    "TARATA",
    "TARD",
    "TARDIER",
    "TARE",
    "TART",
    "TARTED",
    "TARTER",
    "TARTAR",
    "TARTARIC",
    "TARTARE",
    "TARTE",
    "TARTRATE",
    "TARTIER",
    "TAT",
    "TATA",
    "TATER",
    "TATIE",
    "TAU",
    "TAUA",
    "TEA",
    "TEAED",
    "TEAR",
    "TEARER",
    "TEARED",
    "TEARIER",
    "TEAT",
    "TED",
    "TEREDO",
    "TERETE",
    "TETE",
    "TETRA",
    "TETRAD",
    "TETRI",
    "TIC",
    "TIDE",
    "TIDED",
    "TIDIER",
    "TIDIED",
    "TIE",
    "TIED",
    "TIER",
    "TIERED",
    "TIRADE",
    "TIRE",
    "TIRED",
    "TIT",
    "TITI",
    "TITRATE",
    "TITRATED",
    "TITRE",
    "TITER",
    "TIZ",
    "TOAD",
    "TOADIED",
    "TOCO",
    "TOD",
    "TODO",
    "TOE",
    "TOED",
    "TOEA",
    "TOT",
    "TOTARA",
    "TOTE",
    "TOTED",
    "TOTER",
    "TOTIER",
    "TOUR",
    "TOURED",
    "TOURER",
    "TOURTIERE",
    "TRACT",
    "TRACTATE",
    "TRAD",
    "TRADE",
    "TRADED",
    "TRADER",
    "TRADIE",
    "TRA",
    "TREADED",
    "TREADER",
    "TREAT",
    "TREATED",
    "TREATER",
    "TRET",
    "TRICAR",
    "TRICOT",
    "TRIED",
    "TRIER",
    "TRIO",
    "TRIODE",
    "TRITE",
    "TRITER",
    "TRUE",
    "TRUER",
    "TRUED",
    "CZAR",
    "TZAR",
    "TOURACO",
    "UBE",
    "URAEI",
    "URATE",
    "UREA",
    "UREIDE",
    "UREID",
    "URETER",
    "URETERIC",
    "URIC",
    "URTICATE",
    "URTICATED",
    "ACTO",
    "ZAC",
    "ZARDA",
    "ZARI",
    "ZEBRA",
    "ZEBU",
    "ZED",
    "ZETA",
    "ZETETIC",
    "ZIT",
    "ZITI",
    "ZITO",
    "ADBOT",
    "CATBRIER",
    "CITIED",
    "COBOT",
    "DIRTBOARD",
    "EIDE",
    "OCREA",
    "OCREAE",
    "RITARD",
    "RUOTE",
    "ACATER",
    "ACOURI",
    "ACOURIE",
    "ACIDIZE",
    "ACIDIZED",
    "ACRIDID",
    "ACTA",
    "ACUATE",
    "ACUATED",
    "ADAT",
    "ADEAD",
    "ADJURER",
    "AEREATED",
    "AETITE",
    "AJI",
    "AJOURE",
    "ARCTICIZE",
    "ARCTICIZED",
    "ARDEB",
    "ARTER",
    "ARTERITIC",
    "ATER",
    "BOE",
    "BOET",
    "BOETIE",
    "BOETI",
    "BOTA",
    "BOTIJA",
    "BOTIJO",
    "BRUITER",
    "BRUJA",
    "BRUJO",
    "BUBOED",
    "BUCU",
    "CARBURET",
    "CITATE",
    "CITATED",
    "CITER",
    "CITRATED",
    "DADI",
    "DADOED",
    "DEBOARD",
    "DEBOARDED",
    "DIDACT",
    "DIOTIC",
    "ETOURDERIE",
    "ETOURDI",
    "ETOURDIE",
    "EURETIC",
    "IDEAED",
    "IDEOCRATIC",
    "IDIOCRATIC",
    "IDIOTA",
    "IDIOTIZE",
    "IDIOTIZED",
    "JITI",
    "OARER",
    "OBO",
    "OBJURE",
    "OBJURED",
    "OCOTE",
    "OCREATE",
    "OCTADIC",
    "OCTIC",
    "OCTOATE",
    "OCTODE",
    "ODA",
    "ODOURED",
    "OITICICA",
    "OURIE",
    "OUZE",
    "OTARIOID",
    "OUED",
    "OUI",
    "OUZERI",
    "RADEAU",
    "RADICATE",
    "RADICATED",
    "RADIOBE",
    "RADIOIZE",
    "RADIOIZED",
    "RAJOID",
    "RATER",
    "RATICIDE",
    "RATIOED",
    "RATO",
    "RATI",
    "RAZER",
    "RAZET",
    "RAZETEUR",
    "RAZATEUR",
    "REBEAT",
    "REBETIC",
    "REBETE",
    "REBODIED",
    "REBRED",
    "REDACTER",
    "REDACTEUR",
    "REDART",
    "REDARTED",
    "REDATE",
    "REDATED",
    "REDBEARD",
    "REDEAR",
    "REDICTATE",
    "REDICTATED",
    "REDOUBTED",
    "REIRD",
    "REARD",
    "REIRDED",
    "RETOUR",
    "RETOURED",
    "RETREADER",
    "RETREATER",
    "REATA",
    "RIDERED",
    "RIZA",
    "RIZARED",
    "RUBRICIZE",
    "RUBRICIZED",
    "RURU",
    "RIO",
    "TEATED",
    "TITAR",
    "TITIR",
    "TITA",
    "TITE",
    "TODEA",
    "TRADIT",
    "TRADITED",
    "URB"
  ],
  "par": 6,
  "yesterdaysSolution": [
    "WAVEFORM",
    "MILDLY"
  ],
  "yesterdaysSides": [
    "EAI",
    "RLF",
    "OMY",
    "WVD"
  ],
  "isFree": false,
  "editor": "Sam Ezersky",
  "editorImage": "https://storage.googleapis.com/nyt-games-prd.appspot.com/avatars/sam-ezersky.png"
}