{
  "id": 2413,
  "expiration": 1752476400,
  "ourSolution": [
    "QUALIFICATION",
    "NEW"
  ],
  "printDate": "2025-07-13",
  "sides": [
    "QNC",
    "UOF",
    "AWI",
    "LTE"
  ],
  "date": "July 13, 2025",
  "dictionary": [
    "INITIO",
    "ACE",
    "ACINI",
    "ACLINIC",
    "ACONITINE",
    "ACT",
    "ACTANT",
    "ACTIN",
    "ACTINIC",
    "ACTION",
    "ACTUAL",
    "ACTUATION",
    "AEON",
    "EON",
    "AFLOAT",
    "AFT",
    "AFTO",
    "ALANINE",
    "ALFALFA",
    "ALIEN",
    "ALIENATION",
    "ALOE",
    "ALONE",
    "ALU",
    "ALOW",
    "ALULA",
    "ALULAE",
    "ANA",
    "ANACLITIC",
    "ANAL",
    "ANENT",
    "ANEW",
    "ANI",
    "ANILINE",
    "ANION",
    "ANIONIC",
    "ANOA",
    "ANOINT",
    "ANON",
    "ANT",
    "ANTI",
    "ANTIC",
    "ANTICLINE",
    "ANTICLINAL",
    "ANTIQUE",
    "AQUA",
    "AQUANAUT",
    "AQUATIC",
    "AQUATINT",
    "AQUILINE",
    "ATACTIC",
    "ATONAL",
    "ATONE",
    "ATONIC",
    "AUCTION",
    "AUNT",
    "AUNTIE",
    "AUTO",
    "AUTOCUE",
    "AUTOTUNE",
    "CACA",
    "CACAO",
    "CACIQUE",
    "CACTI",
    "CAECA",
    "CECA",
    "CAECAL",
    "CECAL",
    "CAFE",
    "CALCANEI",
    "CALCANEA",
    "CALCANEAL",
    "CALCIC",
    "CALCIFIC",
    "CALCIFICATION",
    "CALCINE",
    "CALCINATION",
    "CALCITIC",
    "CALCITONIN",
    "CALCULATION",
    "CALCULI",
    "CALF",
    "CALICO",
    "CALQUE",
    "CAN",
    "CANAL",
    "CANE",
    "CANINE",
    "CANOE",
    "CANOLA",
    "CANON",
    "CANONIC",
    "CANONICAL",
    "CANT",
    "CANTAL",
    "CANTATA",
    "CANTINA",
    "CANTO",
    "CANTON",
    "CANTONAL",
    "CANTI",
    "TOWN",
    "CAT",
    "CATAFALQUE",
    "CATATONIC",
    "CATION",
    "CATIONIC",
    "CAUL",
    "CAUTION",
    "CEIL",
    "CEILI",
    "CENT",
    "CENTO",
    "QUE",
    "CILICE",
    "CINE",
    "CITATION",
    "CITIFICATION",
    "CLAN",
    "CLAQUE",
    "CLIENT",
    "CLINE",
    "CLINAL",
    "CLINIC",
    "CLINICAL",
    "CLINT",
    "CLIQUE",
    "CLITIC",
    "CLOACA",
    "CLOACAE",
    "CLOACAL",
    "CLONAL",
    "CLONE",
    "CLONIC",
    "CLOQUE",
    "CLOT",
    "CLOWN",
    "CLUE",
    "COACTION",
    "COAL",
    "COALFACE",
    "COALITION",
    "COAT",
    "COATI",
    "COCA",
    "COCO",
    "COCOA",
    "COCOANUT",
    "COCONUT",
    "COEQUAL",
    "COIF",
    "COIL",
    "COIN",
    "COITION",
    "COITAL",
    "COL",
    "COLA",
    "COLIC",
    "COLICIN",
    "COLON",
    "COLONIC",
    "FAUT",
    "CON",
    "CONATION",
    "CONE",
    "CONFECT",
    "CONFECTION",
    "CONFINE",
    "CONFIT",
    "CONFLATION",
    "CONFLICT",
    "CONFLICTUAL",
    "CONFLUENT",
    "CONIC",
    "CONICAL",
    "CONTACT",
    "CONTINENT",
    "CONTINENTAL",
    "CONTINUAL",
    "CONTINUANT",
    "CONTINUATION",
    "CONTINUE",
    "CONTINUA",
    "CONI",
    "COQ",
    "COQUINA",
    "COQUITO",
    "COT",
    "OIL",
    "COW",
    "COWL",
    "COWTOWN",
    "CUE",
    "CUECA",
    "CUI",
    "CULICINE",
    "CUT",
    "CUTIE",
    "CUTIN",
    "FACTO",
    "NON",
    "EAT",
    "EATIN",
    "ECLAT",
    "ECO",
    "ECOCLINE",
    "COLI",
    "ECON",
    "ECONUT",
    "ECOTONE",
    "ECOTONAL",
    "ECOTOWN",
    "ECU",
    "EFIT",
    "EFT",
    "EINA",
    "ENACT",
    "ENACTION",
    "ENATION",
    "ENFANT",
    "ENLACE",
    "ENTICE",
    "EQUAL",
    "EQUANT",
    "EQUATION",
    "EQUATIONAL",
    "EQUIFINAL",
    "EQUINE",
    "EQUITANT",
    "EQUITATION",
    "EWE",
    "FACE",
    "FACILITATION",
    "FACT",
    "FACTION",
    "FACTIONAL",
    "FACTUAL",
    "FACTA",
    "FACULA",
    "FACULAE",
    "FAECAL",
    "FECAL",
    "FALCON",
    "FAN",
    "FANAL",
    "FANATIC",
    "FANATICAL",
    "FANE",
    "FANFIC",
    "FANFICTION",
    "FAT",
    "FATAL",
    "FATCAT",
    "FAUN",
    "FAUNA",
    "FAUNAE",
    "FAUNAL",
    "FEAT",
    "FEINT",
    "FEN",
    "FEU",
    "FEW",
    "FIC",
    "FICTION",
    "FICTIONAL",
    "FIE",
    "FIEF",
    "FIFE",
    "FILO",
    "FIN",
    "FINAL",
    "FINE",
    "FINICAL",
    "FINITO",
    "FINO",
    "FIT",
    "FITNA",
    "FLACON",
    "FLAN",
    "FLAT",
    "FLAUNT",
    "FLAUTA",
    "FLIC",
    "FLINT",
    "FLIT",
    "FLOAT",
    "FLOATIE",
    "FLOC",
    "FLOE",
    "FLOTATION",
    "FLOATATION",
    "FLOW",
    "FLOWLINE",
    "FLOWN",
    "FLU",
    "FLUCTUANT",
    "FLUCTUATION",
    "FLUE",
    "FLUENT",
    "WENT",
    "QUI",
    "ICE",
    "ICON",
    "ICONIC",
    "ICTAL",
    "INACTION",
    "INANE",
    "INANITION",
    "INFANT",
    "INFANTA",
    "INFANTINE",
    "INFATUATION",
    "INFAUNA",
    "INFAUNAL",
    "INFECT",
    "INFECTION",
    "INFLATION",
    "INFLICT",
    "INFLICTION",
    "INFLOW",
    "INFLUENT",
    "INION",
    "INLINE",
    "INOCULANT",
    "INOCULATION",
    "INOCULA",
    "INTACT",
    "INTI",
    "INTO",
    "INTONATION",
    "INTONATIONAL",
    "INTONE",
    "TOTO",
    "INTUIT",
    "INTUITION",
    "INTUITIONAL",
    "INULIN",
    "ION",
    "IONIC",
    "IOTA",
    "ITAL",
    "ITALIC",
    "CAFTAN",
    "QAT",
    "LAC",
    "LACE",
    "LACONIC",
    "LACONICA",
    "LACTATION",
    "LACTATIONAL",
    "LACTIC",
    "LACTONE",
    "LACUNA",
    "LACUNAE",
    "LACUNAL",
    "LANE",
    "LANOLIN",
    "LANTANA",
    "LAT",
    "LATI",
    "LICE",
    "LICIT",
    "LIE",
    "LIEF",
    "LIEN",
    "LIEU",
    "LIFE",
    "LIFT",
    "LIT",
    "LITIE",
    "LILAC",
    "LILO",
    "LINAC",
    "LINE",
    "LINEAL",
    "LINEATION",
    "LINEIN",
    "LINEN",
    "LINO",
    "LINOCUT",
    "LINT",
    "LINTIE",
    "LION",
    "LIQUATION",
    "LIQUEFACTION",
    "LIQUIFACTION",
    "LIQUEFACIENT",
    "LIQUIFACIENT",
    "LOA",
    "LOAF",
    "LOAN",
    "LOCAL",
    "LOCATION",
    "LOCATIONAL",
    "LOCI",
    "LOCIE",
    "LOCO",
    "LOCULI",
    "LOCUTION",
    "LOIN",
    "LOL",
    "LOLCAT",
    "LONE",
    "LOQUAT",
    "LOT",
    "LOTA",
    "LOTI",
    "LOTIC",
    "LOTION",
    "LOW",
    "LOWCUT",
    "LOWE",
    "LOWLIFE",
    "LUAU",
    "LUCE",
    "LUCENT",
    "LUCINE",
    "LULU",
    "LUNA",
    "LUNATIC",
    "LUNATION",
    "LUNE",
    "LUNULA",
    "LUNULAE",
    "LUTINO",
    "LWEI",
    "FICTA",
    "NAE",
    "NAN",
    "NANA",
    "NANO",
    "NANTO",
    "NAOI",
    "NATAL",
    "NATANT",
    "NATATION",
    "NATION",
    "NATIONAL",
    "NAUTICAL",
    "NAUTILI",
    "NEAT",
    "NEF",
    "NENE",
    "NEOCON",
    "NEON",
    "NEONATAL",
    "NEONIC",
    "NEW",
    "NEWT",
    "NEWTON",
    "NICE",
    "NICOTINE",
    "NICOTINIC",
    "NICTATION",
    "NIECE",
    "NIL",
    "NINE",
    "NINON",
    "NIT",
    "NITINOL",
    "NOA",
    "NOCTILUCA",
    "NOCTILUCAE",
    "NOCTILUCENT",
    "NOIL",
    "NOLI",
    "NOLITION",
    "NOLO",
    "NONANE",
    "NONE",
    "NONFAT",
    "NONFICTION",
    "NONFICTIONAL",
    "NONFLUENT",
    "NONI",
    "NONLIFE",
    "NONUNION",
    "NOT",
    "NOTATION",
    "NOTATIONAL",
    "NOTICE",
    "NOTIFICATION",
    "NOTION",
    "NOTIONAL",
    "NOTA",
    "NOTAL",
    "NOW",
    "NOWT",
    "NUIT",
    "NALA",
    "NUN",
    "NUNU",
    "NUT",
    "NUTATION",
    "OAF",
    "OAT",
    "OCA",
    "OCEAN",
    "OCEANIC",
    "OCICAT",
    "OCTAL",
    "OCTANE",
    "OCTANT",
    "OCULI",
    "OILCAN",
    "OLFACTION",
    "OLIO",
    "ONE",
    "ONFLOW",
    "ONION",
    "ONLINE",
    "ONTIC",
    "ONTO",
    "CIT",
    "OTIC",
    "OWE",
    "OWL",
    "OWN",
    "OWT",
    "FACIE",
    "QANAT",
    "QILA",
    "QUILA",
    "QUA",
    "QUALIFICATION",
    "QUALIE",
    "QUANT",
    "QUANTA",
    "QUANTAL",
    "QUANTIC",
    "QUANTIFICATION",
    "QUANTITATION",
    "QUEAN",
    "QUEUE",
    "QUIN",
    "QUINIC",
    "QUININE",
    "QUINOA",
    "QUINOL",
    "QUINOLINE",
    "QUINOLONE",
    "QUINONE",
    "QUINT",
    "QUINTA",
    "QUINTAL",
    "QUIT",
    "LATO",
    "TACAN",
    "TACIT",
    "TACO",
    "TACT",
    "TACTIC",
    "TACTICAL",
    "TACTUAL",
    "TAE",
    "TAL",
    "TALA",
    "TALAQ",
    "TALC",
    "TALI",
    "TALON",
    "TAN",
    "TANTALIC",
    "TANT",
    "TANTO",
    "TAQUITO",
    "TAT",
    "TATA",
    "TATIE",
    "TAU",
    "TAUA",
    "TAUNT",
    "TAUT",
    "TIC",
    "TIE",
    "TIEF",
    "TIENTO",
    "TIN",
    "TINE",
    "TINEA",
    "TINT",
    "TINTO",
    "TIT",
    "TITAN",
    "TITANIC",
    "TITI",
    "TOCO",
    "TOE",
    "TOEA",
    "TOIL",
    "TOLU",
    "TOLUENE",
    "TOLUIC",
    "TON",
    "TONAL",
    "TONALITIC",
    "TONE",
    "TONIC",
    "TONIFICATION",
    "TONTINE",
    "TOQUE",
    "TOT",
    "TOTAL",
    "TOW",
    "TOWLINE",
    "TOWNIE",
    "OEIL",
    "TUAN",
    "TUCOTUCO",
    "TUI",
    "TUITION",
    "TUITIONAL",
    "TUN",
    "TUNA",
    "TUNE",
    "TUNIC",
    "TUNICA",
    "TUNICAE",
    "TUQUE",
    "TUT",
    "TUTU",
    "TWO",
    "TWOC",
    "ULNA",
    "ULNAE",
    "ULU",
    "ULULANT",
    "ULULATION",
    "UNEQUAL",
    "UNFIT",
    "UNI",
    "UNICA",
    "UNIFACE",
    "UNIFICATION",
    "UNIFLOW",
    "UNION",
    "UNIQUE",
    "UNIT",
    "UNLACE",
    "UNLIT",
    "UNTIE",
    "UNTIL",
    "UNTO",
    "INTACTA",
    "WEFT",
    "WEAL",
    "WEAN",
    "WEI",
    "WEN",
    "WON",
    "WOT",
    "WOE",
    "WOLF",
    "WONT",
    "WONTON",
    "WOW",
    "ACTO",
    "ANTILIFE",
    "ANTINATIONAL",
    "CANALICULI",
    "COALIFICATION",
    "COQUI",
    "LAUAN",
    "NONIONIC",
    "CION",
    "ACACINE",
    "ACACIN",
    "ACANONICAL",
    "ACAULINE",
    "ACENE",
    "ACICULA",
    "ACINIC",
    "ACONE",
    "ACONIC",
    "ACONINE",
    "ACONITIC",
    "ACTA",
    "ACTINAL",
    "ACTINE",
    "ACTININ",
    "ACTINOLITIC",
    "ACTINON",
    "ACTINULA",
    "ACTIONAL",
    "ACTON",
    "ACUATION",
    "AEFAUL",
    "AEOLINE",
    "EOLINE",
    "AEONIC",
    "AFION",
    "ANFION",
    "AFLOW",
    "ALALA",
    "ALANTIN",
    "ALATA",
    "ALATION",
    "ALAUNT",
    "ALAN",
    "ALC",
    "ALCE",
    "ALCEA",
    "ALFAQUI",
    "ALIF",
    "ALIQUANT",
    "ALINEATION",
    "ALNICO",
    "ALOIN",
    "ALOINE",
    "ANTA",
    "ANTILUCAN",
    "ANTOECI",
    "ANTU",
    "AULA",
    "AULIC",
    "AULICAL",
    "AUNE",
    "AUTOINFECTION",
    "AUTOINOCULATION",
    "CANALICULATION",
    "CENTAL",
    "CENTONICAL",
    "CITATIONAL",
    "CLIENTAL",
    "COALITIONAL",
    "CUENTO",
    "QUENTO",
    "ENT",
    "FACTICE",
    "FAE",
    "FILON",
    "FLUATATION",
    "INFECTANT",
    "IONENE",
    "IONICAL",
    "IONONE",
    "LACINATO",
    "LACINULA",
    "LOCANT",
    "LOCULATION",
    "LOLA",
    "LOLO",
    "LOWN",
    "LOWEN",
    "LUN",
    "LOWT",
    "NACE",
    "NAEO",
    "NANT",
    "NANTI",
    "NAOW",
    "NAO",
    "NATATIONAL",
    "NAUTIC",
    "NEANIC",
    "NEANT",
    "NEATO",
    "NIEF",
    "NEFIE",
    "NEINEI",
    "NENTA",
    "NINTA",
    "NEOLOCAL",
    "NEU",
    "NEWLINE",
    "NICOTINEAN",
    "NICTITANT",
    "NICTITATION",
    "NIF",
    "NIFE",
    "NITAL",
    "NITON",
    "NIU",
    "NOCENT",
    "NOCTILUCAL",
    "NOCTUA",
    "NOINT",
    "NONACTIN",
    "NONAN",
    "NONENE",
    "NONIC",
    "NONOIC",
    "NOI",
    "NOTATIN",
    "NOWN",
    "NUCIN",
    "NUNATION",
    "NUQUE",
    "NUTANT",
    "NUTATIONAL",
    "NIE",
    "OCEANAUT",
    "OCTACTINAL",
    "OCTANOL",
    "OCTANTAL",
    "OCTATONIC",
    "OCTIC",
    "OCTONAL",
    "OCTONION",
    "OCTINE",
    "OITICICA",
    "OLA",
    "OLATION",
    "OLIFANT",
    "OLOLIUQUI",
    "OLOLIUQUE",
    "OLONA",
    "ONTAL",
    "ONTICAL",
    "UNT",
    "OWNIO",
    "QUANTIFICATIONAL",
    "QUANTON",
    "QUAT",
    "QUEANIE",
    "QUINIE",
    "QUENA",
    "QENA",
    "QUINA",
    "QUINAQUINA",
    "QUINICINE",
    "QUININIC",
    "QUINION",
    "QUINANT",
    "QUINOLIC",
    "QUINTAN",
    "QUINTANT",
    "QUINTIC",
    "QUINTON",
    "TAUTIT",
    "TAUTOCLIN",
    "TAUTOCLINE",
    "TAUTIE",
    "TITA",
    "TITANATION",
    "TITANICAL",
    "TITANITIC",
    "TITIN",
    "TOWNO",
    "TUINA",
    "UNIO",
    "UNIONAL",
    "UNITAL",
    "UNITION",
    "UNLINE",
    "UNLINEAL",
    "UNLUCENT",
    "UNOWN"
  ],
  "par": 6,
  "yesterdaysSolution": [
    "WHODUNIT",
    "TALKY"
  ],
  "yesterdaysSides": [
    "WIL",
    "OTN",
    "YUA",
    "HKD"
  ],
  "isFree": false,
  "editor": "Sam Ezersky",
  "editorImage": "https://storage.googleapis.com/nyt-games-prd.appspot.com/avatars/sam-ezersky.png"
}