{
  "id": 2661,
  "expiration": 1773903600,
  "ourSolution": [
    "QUACKERY",
    "YARDBIRDS"
  ],
  "printDate": "2026-03-18",
  "sides": [
    "YES",
    "CBR",
    "UDK",
    "QIA"
  ],
  "date": "March 18, 2026",
  "dictionary": [
    "ABS",
    "ABACA",
    "ABACAS",
    "ABACK",
    "ABACUS",
    "ABAYA",
    "ABAYAS",
    "ABDABS",
    "ABED",
    "ABIDE",
    "ABIDED",
    "ABSCISIC",
    "ABSURD",
    "ABSURDER",
    "ABURA",
    "ABURAS",
    "ACARA",
    "ACARAS",
    "ACARID",
    "ACARIDS",
    "ACARICIDE",
    "AKARA",
    "AKARAS",
    "ACE",
    "ACED",
    "ACER",
    "ACERS",
    "ACID",
    "ACIDS",
    "ACIDY",
    "ACIDIC",
    "ACK",
    "ACKERS",
    "ACQUIRE",
    "ACQUIRED",
    "ACQUIRER",
    "ACQUIRERS",
    "REUS",
    "ADS",
    "ADEQUACY",
    "ADIEU",
    "ADIEUS",
    "ARABICA",
    "ARABICAS",
    "ARABIS",
    "ARACARI",
    "ARACARIS",
    "ARE",
    "AREA",
    "AREAS",
    "ARECA",
    "ARECAS",
    "ARID",
    "ARIKI",
    "ARIKIS",
    "ARK",
    "ARKS",
    "ARQUEBUS",
    "ARAK",
    "ARSIER",
    "ARSIS",
    "ASCARID",
    "ASCARIS",
    "ASCARIDS",
    "ASCI",
    "ASCUS",
    "ASDIC",
    "ASIDE",
    "ASK",
    "ASKS",
    "ASKED",
    "ASKER",
    "ASKERS",
    "ASKARI",
    "ASKARIS",
    "ASURA",
    "ASURAS",
    "AUBADE",
    "AUCUBA",
    "AUCUBAS",
    "AURA",
    "AURAS",
    "AURAE",
    "AURAR",
    "AUREUS",
    "AUREI",
    "AURIC",
    "AKS",
    "BAS",
    "BAB",
    "BABS",
    "BABA",
    "BABAS",
    "BABACU",
    "BABACUS",
    "BABE",
    "BABIRUSA",
    "BABIRUSAS",
    "BABU",
    "BABUS",
    "BABY",
    "BABIED",
    "BACK",
    "BACKS",
    "BACKED",
    "BACKBAR",
    "BACKBARS",
    "BACKER",
    "BACKERS",
    "BACKIE",
    "BACKY",
    "BACKRUB",
    "BACKRUBS",
    "BACKSIDE",
    "BACKYARD",
    "BACKYARDS",
    "BAD",
    "BADA",
    "BADE",
    "BAE",
    "BAKE",
    "BAKED",
    "BAKER",
    "BAKERS",
    "BAKERY",
    "BAR",
    "BARS",
    "BARA",
    "BARD",
    "BARDS",
    "BARDIC",
    "BARDED",
    "BARDIE",
    "BARDY",
    "BARE",
    "BARER",
    "BARED",
    "BAREBACK",
    "BARK",
    "BARKS",
    "BARKED",
    "BARKADA",
    "BARKADAS",
    "BARKER",
    "BARKERS",
    "BARQUE",
    "BARI",
    "BASIC",
    "BASICS",
    "BASIS",
    "BASK",
    "BASKS",
    "BASKED",
    "BASQUE",
    "EARED",
    "BAUERA",
    "BAUERAS",
    "BAY",
    "BAYA",
    "BAYAS",
    "BAYADERE",
    "BDAY",
    "BEAD",
    "BEADS",
    "BEADED",
    "BEADY",
    "BEADIER",
    "BEAK",
    "BEAKS",
    "BEAKED",
    "BEAKER",
    "BEAKERS",
    "BEAKY",
    "BEAR",
    "BEARS",
    "BEARD",
    "BEARDS",
    "BEARDED",
    "BEARDY",
    "BEARDIER",
    "BEARDIE",
    "BEARER",
    "BEARERS",
    "BEAU",
    "BEAUS",
    "BECARD",
    "BECARDS",
    "BECK",
    "BECKS",
    "BED",
    "BEDS",
    "BEDAD",
    "BEDAUB",
    "BEDAUBS",
    "BEDAUBED",
    "BEDECK",
    "BEDECKS",
    "BEDECKED",
    "BEDSIDE",
    "BEIRA",
    "BEIRAS",
    "BEISA",
    "BEISAS",
    "BERIBERI",
    "BERK",
    "BURK",
    "BURKE",
    "BERKS",
    "BURKS",
    "BIB",
    "BIBS",
    "BIBI",
    "BIBIS",
    "BICE",
    "BICKER",
    "BICKERS",
    "BICKERED",
    "BICKERER",
    "BICKERERS",
    "BICKY",
    "BID",
    "BIDS",
    "BIDARKA",
    "BIDARKAS",
    "BIDE",
    "BIDED",
    "BIDI",
    "BIRI",
    "BIDIS",
    "BIRIS",
    "BIDRI",
    "BIER",
    "BIERS",
    "BIKE",
    "BIKED",
    "BIKER",
    "BIKERS",
    "BIKIE",
    "BIRD",
    "BIRDS",
    "BIRDER",
    "BIRDERS",
    "BIRDIE",
    "BIRDIED",
    "BIS",
    "BISQUE",
    "RABE",
    "BUB",
    "BUCK",
    "BUCKS",
    "BUCKED",
    "BUCKRA",
    "BUCKRAS",
    "BUR",
    "BUREAU",
    "BUREAUS",
    "BURIED",
    "BURKA",
    "BURKAS",
    "BURS",
    "BURSA",
    "BURSAE",
    "BURSAS",
    "BURSAR",
    "BURSARS",
    "BURSARY",
    "BURY",
    "BUS",
    "BUSBAR",
    "BUSBARS",
    "BUSBY",
    "BUSK",
    "BUSKS",
    "BUSKED",
    "BUSKER",
    "BUSKERS",
    "BUSIER",
    "BUSIED",
    "BUY",
    "BUYBACK",
    "BUYBACKS",
    "BYRE",
    "CAB",
    "CABS",
    "CABER",
    "CABERS",
    "CACA",
    "CACK",
    "CACKS",
    "CACKED",
    "CAD",
    "CADS",
    "CADRE",
    "CAECA",
    "CECA",
    "CAKE",
    "CAKED",
    "CAR",
    "CARS",
    "CARABID",
    "CARABIDS",
    "CARACARA",
    "CARACARAS",
    "CARD",
    "CARDS",
    "CARDED",
    "CARDER",
    "CARDERS",
    "CARDIE",
    "CARDI",
    "CARDY",
    "CARDIS",
    "CARE",
    "CARED",
    "CARER",
    "CARERS",
    "CARK",
    "KARK",
    "CARKS",
    "CARKED",
    "KARKS",
    "KARKED",
    "ASADA",
    "CARSICK",
    "CASABA",
    "CASABAS",
    "CASCADE",
    "CASCADED",
    "CASCARA",
    "CASCARAS",
    "CASK",
    "CASKS",
    "CASQUE",
    "CASUS",
    "CAUCUS",
    "CAY",
    "CEBID",
    "CEBIDS",
    "CEDAR",
    "CEDARS",
    "CEDE",
    "CEDED",
    "CEDI",
    "CEDIS",
    "CEIBA",
    "CEIBAS",
    "CERE",
    "QUE",
    "CICADA",
    "CICADAS",
    "CICISBEI",
    "CIDER",
    "CIDERS",
    "CYDER",
    "CYDERS",
    "CIDERY",
    "CIRE",
    "CIRQUE",
    "CIS",
    "CSARDAS",
    "CUB",
    "CUBS",
    "CUBE",
    "CUBED",
    "CUBEB",
    "CUBEBS",
    "CUBIC",
    "CUBICS",
    "CUCK",
    "CUCKS",
    "CUE",
    "CUED",
    "CUEBID",
    "CUEBIDS",
    "CUECA",
    "CUECAS",
    "CUI",
    "CUR",
    "CURS",
    "CURACY",
    "CURARE",
    "CURD",
    "CURDS",
    "CURDY",
    "CURE",
    "CURED",
    "CURER",
    "CURERS",
    "CURIE",
    "CUSCUS",
    "CUSK",
    "CUSKS",
    "CYBER",
    "CYCAD",
    "CYCADS",
    "DAS",
    "DAB",
    "DABS",
    "DACE",
    "DAD",
    "DADS",
    "DADA",
    "DADAS",
    "DAK",
    "DAKS",
    "DARE",
    "DARED",
    "DARER",
    "DARERS",
    "DARK",
    "DARKER",
    "DARKS",
    "DAUB",
    "DAUBS",
    "DAUBED",
    "DAUBE",
    "DAUBER",
    "DAUBERS",
    "DAY",
    "DAYBED",
    "DAYBEDS",
    "DAYCARE",
    "DEAD",
    "DEADER",
    "DEAR",
    "DEARER",
    "DEARS",
    "DEARIE",
    "DEB",
    "DEBS",
    "DEBAR",
    "DEBARS",
    "DEBARK",
    "DEBARKS",
    "DEBARKED",
    "DEBEAK",
    "DEBEAKS",
    "DEBEAKED",
    "DEBUR",
    "DEBURS",
    "DEBUS",
    "DECAD",
    "DECADS",
    "DECADE",
    "DECAY",
    "DECIDE",
    "DECIDED",
    "DECIDER",
    "DECIDERS",
    "DECK",
    "DECKS",
    "DECKED",
    "DEICER",
    "DEICERS",
    "DEICIDE",
    "DEID",
    "DEKE",
    "DEKED",
    "DEQUEUE",
    "DEQUEUED",
    "DER",
    "DERE",
    "DERIDE",
    "DERIDED",
    "DERIDER",
    "DERIDERS",
    "DERISK",
    "DERISKS",
    "DERISKED",
    "DEUCE",
    "DEUCED",
    "DEUS",
    "DIB",
    "DIBS",
    "DIBASIC",
    "DICE",
    "DICED",
    "DICER",
    "DICERS",
    "DICIER",
    "DICK",
    "DICKS",
    "DICKER",
    "DICKERS",
    "DICKERED",
    "DICKERER",
    "DICKERERS",
    "DID",
    "DIDI",
    "DIDIS",
    "DIE",
    "DIED",
    "DIEBACK",
    "DIKE",
    "DIRE",
    "DIRER",
    "DIRK",
    "DIRKS",
    "DIS",
    "DISBAR",
    "DISBARS",
    "DISC",
    "DISCS",
    "DISK",
    "DISKS",
    "DISCARD",
    "DISCARDS",
    "DISCARDED",
    "DISCUS",
    "DIYA",
    "DIYAS",
    "CAUSA",
    "DRAB",
    "DRABS",
    "DRACK",
    "DRAKE",
    "DRAY",
    "DREAD",
    "DREADS",
    "DREADED",
    "DREAR",
    "DREARY",
    "DREARIER",
    "DRECK",
    "DREK",
    "DRECKY",
    "DRIBS",
    "DRIED",
    "DRUB",
    "DRUBS",
    "DRY",
    "DRIER",
    "DRYAD",
    "DRYADS",
    "DRYAS",
    "DRIERS",
    "DYAD",
    "DYADS",
    "DYADIC",
    "DIKED",
    "EAR",
    "EARS",
    "EASIER",
    "EBIKE",
    "ECAD",
    "ECADS",
    "ECARD",
    "ECARDS",
    "ECU",
    "ECUS",
    "EIDER",
    "EIDERS",
    "EKE",
    "EKED",
    "EQUID",
    "EQUIDS",
    "ERA",
    "ERAS",
    "ERASURE",
    "ERE",
    "EREADER",
    "EREADERS",
    "ERICA",
    "ERICAS",
    "ERK",
    "ERKS",
    "ERUCIC",
    "EUCY",
    "EUREKA",
    "EUREKAS",
    "AERIE",
    "ARABIC",
    "QUI",
    "IBERIS",
    "IBIS",
    "ICE",
    "ICED",
    "ICK",
    "ICKY",
    "ICKIER",
    "ICY",
    "ICIER",
    "IDS",
    "IDE",
    "IDEA",
    "IDEAS",
    "RECUE",
    "IRADE",
    "IRE",
    "IRIE",
    "IRIS",
    "IRK",
    "IRKS",
    "IRKED",
    "KAS",
    "KABAKA",
    "KABAKAS",
    "KAKA",
    "KAKAS",
    "KAKI",
    "KAKIS",
    "KARA",
    "KARAS",
    "KARAKA",
    "KARAKAS",
    "KAURI",
    "KAURIS",
    "KAY",
    "KAYAK",
    "KAYAKS",
    "KAYAKED",
    "KAYAKER",
    "KAYAKERS",
    "KEA",
    "KEAS",
    "KEAKI",
    "KEAKIS",
    "KEBAB",
    "KEBABS",
    "KEBAYA",
    "KEBAYAS",
    "KECK",
    "KECKS",
    "KECKED",
    "KED",
    "KEDS",
    "KERERU",
    "KERERUS",
    "KIBE",
    "KICK",
    "KICKS",
    "KICKED",
    "KICKBACK",
    "KICKBACKS",
    "KICKER",
    "KICKERS",
    "KICKY",
    "KICKIER",
    "KID",
    "KIDS",
    "KIEKIE",
    "KIER",
    "KIERS",
    "KIERIE",
    "KIRK",
    "KIRKS",
    "KIRKYARD",
    "KIRKYARDS",
    "KRAY",
    "KRIS",
    "KYU",
    "KYUS",
    "REA",
    "CEREUS",
    "CADI",
    "KADI",
    "KADIS",
    "CADIS",
    "QUA",
    "QUACK",
    "QUACKS",
    "QUACKED",
    "QUACKERY",
    "QUAD",
    "QUADS",
    "QUADBIKE",
    "QUADRIC",
    "QUADRICS",
    "QUAKE",
    "QUAKED",
    "QUAKY",
    "QUAKIER",
    "QUARE",
    "QUARK",
    "QUARKS",
    "QUASAR",
    "QUASARS",
    "QUAY",
    "QUEASIER",
    "QUERIDA",
    "QUERIDAS",
    "KERIDA",
    "KERIDAS",
    "QUERY",
    "QUERIED",
    "QUEUE",
    "QUEUED",
    "QUICK",
    "QUICKER",
    "QUICKS",
    "QUICKIE",
    "QUID",
    "QUIDS",
    "QUIRE",
    "QUIRK",
    "QUIRKS",
    "QUIRKED",
    "QUIRKY",
    "QUIRKIER",
    "RABI",
    "RABID",
    "RACE",
    "RACED",
    "RACECARD",
    "RACECARDS",
    "RACER",
    "RACERS",
    "RACK",
    "RACKS",
    "RACKED",
    "RACY",
    "RACIER",
    "RAD",
    "RADS",
    "RADAR",
    "RADARS",
    "RADIUS",
    "RAKE",
    "RAKED",
    "RAKER",
    "RAKERS",
    "RAKI",
    "RAKSASA",
    "RAKSASAS",
    "RARA",
    "RARE",
    "RARER",
    "RARK",
    "RARKS",
    "RARKED",
    "RASA",
    "RASAS",
    "RAS",
    "RAY",
    "REACQUIRE",
    "REACQUIRED",
    "READ",
    "READS",
    "READER",
    "READERS",
    "READY",
    "READIER",
    "READIED",
    "REAR",
    "REARS",
    "REARED",
    "REARER",
    "REARERS",
    "REBAB",
    "REBABS",
    "REBAR",
    "REBARS",
    "REBEC",
    "REBECK",
    "REBECS",
    "REBECKS",
    "REBID",
    "REBIDS",
    "REBURY",
    "REBURIED",
    "REBUS",
    "REC",
    "RECS",
    "RECEDE",
    "RECEDED",
    "RECK",
    "RECKS",
    "RECKED",
    "RECUR",
    "RECURS",
    "RED",
    "REDS",
    "REDBACK",
    "REDBACKS",
    "REDBEDS",
    "REDCEDAR",
    "REDCEDARS",
    "REDE",
    "REDED",
    "REDID",
    "REIKI",
    "REQUIRE",
    "REQUIRED",
    "REQUIRER",
    "REQUIRERS",
    "REREAD",
    "REREADS",
    "RIB",
    "RIBS",
    "RICE",
    "RICED",
    "RICER",
    "RICERS",
    "RICK",
    "RICKS",
    "RICKED",
    "RICKRACK",
    "RID",
    "RIDS",
    "RIDE",
    "RIDER",
    "RIDERS",
    "RIDIC",
    "RISK",
    "RISKS",
    "RISKED",
    "RISKY",
    "RISKIER",
    "RISQUE",
    "RUA",
    "RUAS",
    "RUB",
    "RUBS",
    "RUBE",
    "RUBY",
    "RUCK",
    "RUCKS",
    "RUCKED",
    "RUCKSACK",
    "RUCKSACKS",
    "RUE",
    "RUED",
    "RUSA",
    "RUSAS",
    "RUS",
    "RUSK",
    "RUSKS",
    "RYU",
    "RYUS",
    "SAB",
    "SABS",
    "SABICU",
    "SABICUS",
    "SABER",
    "SABERS",
    "SABERED",
    "SAC",
    "SACS",
    "SACK",
    "SACKS",
    "SACKED",
    "SAD",
    "SADSACK",
    "SADSACKS",
    "SAE",
    "SAKE",
    "SAKER",
    "SAKERS",
    "SAKI",
    "SAKIS",
    "SARD",
    "SARDAR",
    "SIRDAR",
    "SARDARS",
    "SIRDARS",
    "SARDIUS",
    "SARI",
    "SARIS",
    "SARK",
    "SARKS",
    "SARKAR",
    "SARKARS",
    "SARKY",
    "SARKIER",
    "SARUS",
    "SAUCE",
    "SAUCED",
    "SAUCER",
    "SAUCERS",
    "SAUCIER",
    "SAUCIERS",
    "SAUCY",
    "SAURY",
    "SAUSIE",
    "SAY",
    "SAYID",
    "SAYIDS",
    "SCAB",
    "SCABS",
    "SCAD",
    "SCADS",
    "SCAR",
    "SCARS",
    "SCARAB",
    "SCARABS",
    "SCARABAEID",
    "SCARABAEIDS",
    "SCARE",
    "SCARED",
    "SCARER",
    "SCARERS",
    "SCARY",
    "SCARIER",
    "SCAUR",
    "SCAURS",
    "SCIRE",
    "SCUBA",
    "SCUBAS",
    "SIB",
    "SIBS",
    "SIC",
    "SICS",
    "SICKED",
    "SICE",
    "SICK",
    "SICKER",
    "SICKS",
    "SICKBAY",
    "SICKBED",
    "SICKBEDS",
    "SICKIE",
    "SIDA",
    "SIDAS",
    "SIDE",
    "SIDED",
    "SIDEBAR",
    "SIDEBARS",
    "SIDECAR",
    "SIDECARS",
    "SIDEKICK",
    "SIDEKICKS",
    "SIKA",
    "SIKAS",
    "SIKE",
    "SIR",
    "SIRS",
    "SIRE",
    "SIRED",
    "SIS",
    "SKA",
    "SKED",
    "SKEDS",
    "SKI",
    "SKIS",
    "SKIED",
    "SKID",
    "SKIDS",
    "SKIER",
    "SKIERS",
    "SKY",
    "SKYR",
    "SUQ",
    "SUQS",
    "SQUAB",
    "SQUABS",
    "SQUAD",
    "SQUADS",
    "SQUARE",
    "SQUARER",
    "SQUARED",
    "SQUARERS",
    "SQUARK",
    "SQUARKS",
    "SQUEAK",
    "SQUEAKS",
    "SQUEAKED",
    "SQUEAKER",
    "SQUEAKERS",
    "SQUEAKY",
    "SQUEAKIER",
    "SQUIB",
    "SQUIBS",
    "SQUICK",
    "SQUICKS",
    "SQUICKED",
    "SQUICKY",
    "SQUICKIER",
    "SQUID",
    "SQUIDS",
    "SQUIRE",
    "SQUIRED",
    "DECISIS",
    "SUB",
    "SUBS",
    "SUBACID",
    "SUBEDAR",
    "SUBEDARS",
    "SUBSIDE",
    "SUBSIDED",
    "SUBSIDY",
    "SUCK",
    "SUCKS",
    "SUCKED",
    "SUCKER",
    "SUCKERS",
    "SUCKERED",
    "SUCKY",
    "SUCKIER",
    "SUE",
    "SUED",
    "SUER",
    "SUERS",
    "SUEDE",
    "SUICIDE",
    "SUICIDED",
    "SUI",
    "SURA",
    "SURAS",
    "SURD",
    "SURDS",
    "SURE",
    "SURER",
    "SUS",
    "UAKARI",
    "UAKARIS",
    "UBAC",
    "UBACS",
    "UBE",
    "UBI",
    "UBIS",
    "URAEUS",
    "URAEI",
    "UREA",
    "UREIDE",
    "UREID",
    "UREIDS",
    "URIC",
    "URUS",
    "USURER",
    "USURERS",
    "USURY",
    "YADA",
    "YAK",
    "YAKS",
    "YACK",
    "YACKS",
    "YACKED",
    "YACKER",
    "YARAK",
    "YARD",
    "YARDS",
    "YDS",
    "YARDED",
    "YARDBIRD",
    "YARDBIRDS",
    "YARE",
    "YAS",
    "YAY",
    "YARK",
    "YARKS",
    "YARKED",
    "YIDAKI",
    "YIDAKIS",
    "YIKE",
    "YUCA",
    "YUCAS",
    "YUCK",
    "YUCKS",
    "YUCKED",
    "YUCKY",
    "YUCKIER",
    "YUS",
    "BABKA",
    "BABKAS",
    "CARIBE",
    "CERIC",
    "DISKED",
    "EIDE",
    "KIR",
    "QUAKIE",
    "RACECAR",
    "RACECARS",
    "REBAKED",
    "SKRIED",
    "ABAC",
    "ABACS",
    "ABASIC",
    "ABASK",
    "ABEAR",
    "ABEARS",
    "ABEARED",
    "ABECEDARY",
    "ABIDER",
    "ABIDERS",
    "ABIU",
    "ABIUS",
    "ABKARI",
    "ABKARIS",
    "ABY",
    "ABUY",
    "ACARUS",
    "ACEDY",
    "ACKER",
    "ACQUIRY",
    "ACQUIS",
    "ADEAD",
    "ADIKAR",
    "ADRADIUS",
    "AERY",
    "AKE",
    "AKEAKE",
    "ARABA",
    "ARABAS",
    "ARDEB",
    "ARDEBS",
    "ARQUEBUSADE",
    "ARQUEBUSIER",
    "ARQUEBUSIERS",
    "ASKAR",
    "ASKARS",
    "AYRE",
    "BABERY",
    "BAREBACKER",
    "BAREBACKERS",
    "BASA",
    "BASAS",
    "BUBA",
    "BUBAS",
    "BUSBIED",
    "BUCU",
    "DADI",
    "DADIS",
    "DISCARDER",
    "DISCARDERS",
    "EARSAY",
    "ICEQUAKE",
    "ICER",
    "ICERS",
    "IDEAED",
    "KIYAKI",
    "KIKAY",
    "KASIDA",
    "QUASIDA",
    "QUAB",
    "QUABS",
    "QUACKER",
    "QUACKERS",
    "QUACKY",
    "QUADRA",
    "QUADRAS",
    "QUADRIBASIC",
    "QUAERE",
    "QUAERED",
    "QUECK",
    "QUEK",
    "QUECKS",
    "QUECKED",
    "QUERIER",
    "QUERIERS",
    "QUEUER",
    "QUEUERS",
    "QUIB",
    "QUIBS",
    "QUIRED",
    "QUIS",
    "QUISBY",
    "QUISCUS",
    "RAB",
    "RABS",
    "RABIC",
    "RACKER",
    "RACKERS",
    "RACKIE",
    "RADEAU",
    "RAKERY",
    "RAKIYA",
    "RAKSASI",
    "RAKSI",
    "RASURE",
    "RAUREKAU",
    "RAURIKAU",
    "RAURAKAU",
    "RAUREKA",
    "RAUREKAUS",
    "RAURIKI",
    "RARIKI",
    "RAURIKIS",
    "RAYA",
    "REAK",
    "REAKS",
    "REBACK",
    "REBACKS",
    "REBACKED",
    "REBAKE",
    "REBUY",
    "RECEDER",
    "RECEDERS",
    "REDBEARD",
    "REDBEARDS",
    "REDEAR",
    "REDEARS",
    "REDECIDE",
    "REDECIDED",
    "REDECK",
    "REDECKS",
    "REDECKED",
    "REDSIDE",
    "REIRD",
    "REARD",
    "REIRDS",
    "REIRDED",
    "REIS",
    "RICEBIRD",
    "RICEBIRDS",
    "RICKER",
    "RICKERS",
    "RICKYARD",
    "RICKYARDS",
    "RIDERED",
    "RIK",
    "RISKER",
    "RISKERS",
    "RUICE",
    "RUBUS",
    "RUCKSACKED",
    "RURU",
    "RURUS",
    "RUSCUS",
    "RUSKIE",
    "RUSKY",
    "RYA",
    "RYAS",
    "SADIC",
    "SAYA",
    "SAYAS",
    "SCIURID",
    "SCIURIDS",
    "SARIR",
    "SID",
    "SIDS",
    "SIDER",
    "SIDERS",
    "SIDERIC",
    "SIDY",
    "SKYRIDE",
    "SUBA",
    "SUBAS",
    "SUBAK",
    "SUBAKS",
    "SUBARID",
    "SUBEDARI",
    "SUBEDARIS",
    "SUBER",
    "SUBERIC",
    "YAYA",
    "YAYAS"
  ],
  "par": 5,
  "yesterdaysSolution": [
    "MAKO",
    "OBTRUSIVE"
  ],
  "yesterdaysSides": [
    "SEB",
    "RAO",
    "IKM",
    "TUV"
  ],
  "isFree": false,
  "editor": "Sam Ezersky",
  "editorImage": "https://storage.googleapis.com/nyt-games-prd.appspot.com/avatars/sam-ezersky.png"
}